Workbook

Sheet Guide
B2: ✦ BUDGET PRO ✦
B3: Votre tracker financier personnel — élégant, intelligent, efficace
B6: 🚀 DÉMARRAGE RAPIDE
B7: 1. | C7: Ouvre l'onglet du mois en cours (ex: Janvier)
B8: 2. | C8: Saisis tes budgets prévus en colonne B pour chaque catégorie
B9: 3. | C9: Chaque semaine, mets à jour la colonne C avec les montants réels
B10: 4. | C10: Les colonnes D, E, F et G se calculent automatiquement
B12: 🎨 CODE COULEURS
B13: 🟢 | C13: Moins de 80% du budget utilisé — tu gères !
B14: 🟡 | C14: Entre 80% et 100% — sois vigilant(e)
B15: 🔴 | C15: Budget dépassé — action requise
B16: ⬜ | C16: Rien de saisi
B18: 📊 SECTIONS DU MOIS
B19: 💰 | C19: REVENUS — tous tes revenus du mois
B20: 🏠 | C20: DÉPENSES FIXES — charges incompressibles
B21: 🛒 | C21: DÉPENSES VARIABLES — dépenses du quotidien
B22: 💳 | C22: CRÉDITS — remboursements en cours
B23: 🏦 | C23: ÉPARGNE — ce que tu mets de côté
B25: 📈 DASHBOARD | C25: Onglet récapitulatif annuel — graphiques et KPIs générés automatiquement
B27: 💡 ASTUCE | C27: Personnalise les noms de catégories directement dans les cellules

Sheet Janvier
A1: ✦ JANVIER ✦
A2: Catégorie | B2: Budget prévu | C2: Réel dépensé | D2: Écart | E2: % utilisé | F2: Progression
A3: 💰 REVENUS
A4: Salaire net | B4: 0 | C4: 0 | D4: =B4-C4 | E4: =IF(B4=0,"—",C4/B4) | F4: =IF(B4=0,"",REPT("▓",MIN(20,INT(C4/B4*20)))&REPT("░",MAX(0,20-MIN(20,INT(C4/B4*20))))) | G4: =IF(C4=0,"⬜",IF(C4/B4<0.8,"🟢",IF(C4/B4<=1,"🟡","🔴")))
A5: Freelance / Side | B5: 0 | C5: 0 | D5: =B5-C5 | E5: =IF(B5=0,"—",C5/B5) | F5: =IF(B5=0,"",REPT("▓",MIN(20,INT(C5/B5*20)))&REPT("░",MAX(0,20-MIN(20,INT(C5/B5*20))))) | G5: =IF(C5=0,"⬜",IF(C5/B5<0.8,"🟢",IF(C5/B5<=1,"🟡","🔴")))
A6: Aides / APL | B6: 0 | C6: 0 | D6: =B6-C6 | E6: =IF(B6=0,"—",C6/B6) | F6: =IF(B6=0,"",REPT("▓",MIN(20,INT(C6/B6*20)))&REPT("░",MAX(0,20-MIN(20,INT(C6/B6*20))))) | G6: =IF(C6=0,"⬜",IF(C6/B6<0.8,"🟢",IF(C6/B6<=1,"🟡","🔴")))
A7: Autres revenus | B7: 0 | C7: 0 | D7: =B7-C7 | E7: =IF(B7=0,"—",C7/B7) | F7: =IF(B7=0,"",REPT("▓",MIN(20,INT(C7/B7*20)))&REPT("░",MAX(0,20-MIN(20,INT(C7/B7*20))))) | G7: =IF(C7=0,"⬜",IF(C7/B7<0.8,"🟢",IF(C7/B7<=1,"🟡","🔴")))
A8: Total Revenus | B8: =SUM(B4:B7) | C8: =SUM(C4:C7) | D8: =SUM(D4:D7) | E8: =IF(B8=0,0,C8/B8) | F8: =IF(B8=0,"",REPT("▓",MIN(20,INT(C8/B8*20)))&REPT("░",MAX(0,20-MIN(20,INT(C8/B8*20)))))
A10: 🏠 DÉPENSES FIXES
A11: Loyer / Crédit immo | B11: 0 | C11: 0 | D11: =B11-C11 | E11: =IF(B11=0,"—",C11/B11) | F11: =IF(B11=0,"",REPT("▓",MIN(20,INT(C11/B11*20)))&REPT("░",MAX(0,20-MIN(20,INT(C11/B11*20))))) | G11: =IF(C11=0,"⬜",IF(C11/B11<0.8,"🟢",IF(C11/B11<=1,"🟡","🔴")))
A12: Assurances | B12: 0 | C12: 0 | D12: =B12-C12 | E12: =IF(B12=0,"—",C12/B12) | F12: =IF(B12=0,"",REPT("▓",MIN(20,INT(C12/B12*20)))&REPT("░",MAX(0,20-MIN(20,INT(C12/B12*20))))) | G12: =IF(C12=0,"⬜",IF(C12/B12<0.8,"🟢",IF(C12/B12<=1,"🟡","🔴")))
A13: Abonnements | B13: 0 | C13: 0 | D13: =B13-C13 | E13: =IF(B13=0,"—",C13/B13) | F13: =IF(B13=0,"",REPT("▓",MIN(20,INT(C13/B13*20)))&REPT("░",MAX(0,20-MIN(20,INT(C13/B13*20))))) | G13: =IF(C13=0,"⬜",IF(C13/B13<0.8,"🟢",IF(C13/B13<=1,"🟡","🔴")))
A14: Téléphone / Internet | B14: 0 | C14: 0 | D14: =B14-C14 | E14: =IF(B14=0,"—",C14/B14) | F14: =IF(B14=0,"",REPT("▓",MIN(20,INT(C14/B14*20)))&REPT("░",MAX(0,20-MIN(20,INT(C14/B14*20))))) | G14: =IF(C14=0,"⬜",IF(C14/B14<0.8,"🟢",IF(C14/B14<=1,"🟡","🔴")))
A15: Total Fixes | B15: =SUM(B11:B14) | C15: =SUM(C11:C14) | D15: =SUM(D11:D14) | E15: =IF(B15=0,0,C15/B15) | F15: =IF(B15=0,"",REPT("▓",MIN(20,INT(C15/B15*20)))&REPT("░",MAX(0,20-MIN(20,INT(C15/B15*20)))))
A17: 🛒 DÉPENSES VARIABLES
A18: Alimentation | B18: 0 | C18: 0 | D18: =B18-C18 | E18: =IF(B18=0,"—",C18/B18) | F18: =IF(B18=0,"",REPT("▓",MIN(20,INT(C18/B18*20)))&REPT("░",MAX(0,20-MIN(20,INT(C18/B18*20))))) | G18: =IF(C18=0,"⬜",IF(C18/B18<0.8,"🟢",IF(C18/B18<=1,"🟡","🔴")))
A19: Transport | B19: 0 | C19: 0 | D19: =B19-C19 | E19: =IF(B19=0,"—",C19/B19) | F19: =IF(B19=0,"",REPT("▓",MIN(20,INT(C19/B19*20)))&REPT("░",MAX(0,20-MIN(20,INT(C19/B19*20))))) | G19: =IF(C19=0,"⬜",IF(C19/B19<0.8,"🟢",IF(C19/B19<=1,"🟡","🔴")))
A20: Santé | B20: 0 | C20: 0 | D20: =B20-C20 | E20: =IF(B20=0,"—",C20/B20) | F20: =IF(B20=0,"",REPT("▓",MIN(20,INT(C20/B20*20)))&REPT("░",MAX(0,20-MIN(20,INT(C20/B20*20))))) | G20: =IF(C20=0,"⬜",IF(C20/B20<0.8,"🟢",IF(C20/B20<=1,"🟡","🔴")))
A21: Loisirs | B21: 0 | C21: 0 | D21: =B21-C21 | E21: =IF(B21=0,"—",C21/B21) | F21: =IF(B21=0,"",REPT("▓",MIN(20,INT(C21/B21*20)))&REPT("░",MAX(0,20-MIN(20,INT(C21/B21*20))))) | G21: =IF(C21=0,"⬜",IF(C21/B21<0.8,"🟢",IF(C21/B21<=1,"🟡","🔴")))
A22: Shopping | B22: 0 | C22: 0 | D22: =B22-C22 | E22: =IF(B22=0,"—",C22/B22) | F22: =IF(B22=0,"",REPT("▓",MIN(20,INT(C22/B22*20)))&REPT("░",MAX(0,20-MIN(20,INT(C22/B22*20))))) | G22: =IF(C22=0,"⬜",IF(C22/B22<0.8,"🟢",IF(C22/B22<=1,"🟡","🔴")))
A23: Restaurant | B23: 0 | C23: 0 | D23: =B23-C23 | E23: =IF(B23=0,"—",C23/B23) | F23: =IF(B23=0,"",REPT("▓",MIN(20,INT(C23/B23*20)))&REPT("░",MAX(0,20-MIN(20,INT(C23/B23*20))))) | G23: =IF(C23=0,"⬜",IF(C23/B23<0.8,"🟢",IF(C23/B23<=1,"🟡","🔴")))
A24: Beauté | B24: 0 | C24: 0 | D24: =B24-C24 | E24: =IF(B24=0,"—",C24/B24) | F24: =IF(B24=0,"",REPT("▓",MIN(20,INT(C24/B24*20)))&REPT("░",MAX(0,20-MIN(20,INT(C24/B24*20))))) | G24: =IF(C24=0,"⬜",IF(C24/B24<0.8,"🟢",IF(C24/B24<=1,"🟡","🔴")))
A25: Autre | B25: 0 | C25: 0 | D25: =B25-C25 | E25: =IF(B25=0,"—",C25/B25) | F25: =IF(B25=0,"",REPT("▓",MIN(20,INT(C25/B25*20)))&REPT("░",MAX(0,20-MIN(20,INT(C25/B25*20))))) | G25: =IF(C25=0,"⬜",IF(C25/B25<0.8,"🟢",IF(C25/B25<=1,"🟡","🔴")))
A26: Total Variables | B26: =SUM(B18:B25) | C26: =SUM(C18:C25) | D26: =SUM(D18:D25) | E26: =IF(B26=0,0,C26/B26) | F26: =IF(B26=0,"",REPT("▓",MIN(20,INT(C26/B26*20)))&REPT("░",MAX(0,20-MIN(20,INT(C26/B26*20)))))
A28: 💳 CRÉDITS
A29: Crédit auto | B29: 0 | C29: 0 | D29: =B29-C29 | E29: =IF(B29=0,"—",C29/B29) | F29: =IF(B29=0,"",REPT("▓",MIN(20,INT(C29/B29*20)))&REPT("░",MAX(0,20-MIN(20,INT(C29/B29*20))))) | G29: =IF(C29=0,"⬜",IF(C29/B29<0.8,"🟢",IF(C29/B29<=1,"🟡","🔴")))
A30: Crédit conso | B30: 0 | C30: 0 | D30: =B30-C30 | E30: =IF(B30=0,"—",C30/B30) | F30: =IF(B30=0,"",REPT("▓",MIN(20,INT(C30/B30*20)))&REPT("░",MAX(0,20-MIN(20,INT(C30/B30*20))))) | G30: =IF(C30=0,"⬜",IF(C30/B30<0.8,"🟢",IF(C30/B30<=1,"🟡","🔴")))
A31: Autre crédit | B31: 0 | C31: 0 | D31: =B31-C31 | E31: =IF(B31=0,"—",C31/B31) | F31: =IF(B31=0,"",REPT("▓",MIN(20,INT(C31/B31*20)))&REPT("░",MAX(0,20-MIN(20,INT(C31/B31*20))))) | G31: =IF(C31=0,"⬜",IF(C31/B31<0.8,"🟢",IF(C31/B31<=1,"🟡","🔴")))
A32: Total Crédits | B32: =SUM(B29:B31) | C32: =SUM(C29:C31) | D32: =SUM(D29:D31) | E32: =IF(B32=0,0,C32/B32) | F32: =IF(B32=0,"",REPT("▓",MIN(20,INT(C32/B32*20)))&REPT("░",MAX(0,20-MIN(20,INT(C32/B32*20)))))
A34: 🏦 ÉPARGNE
A35: Livret A | B35: 0 | C35: 0 | D35: =B35-C35 | E35: =IF(B35=0,"—",C35/B35) | F35: =IF(B35=0,"",REPT("▓",MIN(20,INT(C35/B35*20)))&REPT("░",MAX(0,20-MIN(20,INT(C35/B35*20))))) | G35: =IF(C35=0,"⬜",IF(C35/B35<0.8,"🟢",IF(C35/B35<=1,"🟡","🔴")))
A36: PEL / CEL | B36: 0 | C36: 0 | D36: =B36-C36 | E36: =IF(B36=0,"—",C36/B36) | F36: =IF(B36=0,"",REPT("▓",MIN(20,INT(C36/B36*20)))&REPT("░",MAX(0,20-MIN(20,INT(C36/B36*20))))) | G36: =IF(C36=0,"⬜",IF(C36/B36<0.8,"🟢",IF(C36/B36<=1,"🟡","🔴")))
A37: Assurance-vie | B37: 0 | C37: 0 | D37: =B37-C37 | E37: =IF(B37=0,"—",C37/B37) | F37: =IF(B37=0,"",REPT("▓",MIN(20,INT(C37/B37*20)))&REPT("░",MAX(0,20-MIN(20,INT(C37/B37*20))))) | G37: =IF(C37=0,"⬜",IF(C37/B37<0.8,"🟢",IF(C37/B37<=1,"🟡","🔴")))
A38: Investissements | B38: 0 | C38: 0 | D38: =B38-C38 | E38: =IF(B38=0,"—",C38/B38) | F38: =IF(B38=0,"",REPT("▓",MIN(20,INT(C38/B38*20)))&REPT("░",MAX(0,20-MIN(20,INT(C38/B38*20))))) | G38: =IF(C38=0,"⬜",IF(C38/B38<0.8,"🟢",IF(C38/B38<=1,"🟡","🔴")))
A39: Total Épargne | B39: =SUM(B35:B38) | C39: =SUM(C35:C38) | D39: =SUM(D35:D38) | E39: =IF(B39=0,0,C39/B39) | F39: =IF(B39=0,"",REPT("▓",MIN(20,INT(C39/B39*20)))&REPT("░",MAX(0,20-MIN(20,INT(C39/B39*20)))))
A42: ✦ BILAN DU MOIS
A43: 💰 Total Revenus | F43: =C8
A44: 💸 Total Dépenses | F44: =C15+C26+C32
A45: 📊 Solde du mois | F45: =C8-(C15+C26+C32)
A46: 🎯 Taux d'épargne | F46: =IF(C8=0,0,(C8-(C15+C26+C32))/C8)
A47: 🏦 Épargne réelle | F47: =C39

Sheet Fevrier
A1: ✦ FÉVRIER ✦
A2: Catégorie | B2: Budget prévu | C2: Réel dépensé | D2: Écart | E2: % utilisé | F2: Progression
A3: 💰 REVENUS
A4: Salaire net | B4: 0 | C4: 0 | D4: =B4-C4 | E4: =IF(B4=0,"—",C4/B4) | F4: =IF(B4=0,"",REPT("▓",MIN(20,INT(C4/B4*20)))&REPT("░",MAX(0,20-MIN(20,INT(C4/B4*20))))) | G4: =IF(C4=0,"⬜",IF(C4/B4<0.8,"🟢",IF(C4/B4<=1,"🟡","🔴")))
A5: Freelance / Side | B5: 0 | C5: 0 | D5: =B5-C5 | E5: =IF(B5=0,"—",C5/B5) | F5: =IF(B5=0,"",REPT("▓",MIN(20,INT(C5/B5*20)))&REPT("░",MAX(0,20-MIN(20,INT(C5/B5*20))))) | G5: =IF(C5=0,"⬜",IF(C5/B5<0.8,"🟢",IF(C5/B5<=1,"🟡","🔴")))
A6: Aides / APL | B6: 0 | C6: 0 | D6: =B6-C6 | E6: =IF(B6=0,"—",C6/B6) | F6: =IF(B6=0,"",REPT("▓",MIN(20,INT(C6/B6*20)))&REPT("░",MAX(0,20-MIN(20,INT(C6/B6*20))))) | G6: =IF(C6=0,"⬜",IF(C6/B6<0.8,"🟢",IF(C6/B6<=1,"🟡","🔴")))
A7: Autres revenus | B7: 0 | C7: 0 | D7: =B7-C7 | E7: =IF(B7=0,"—",C7/B7) | F7: =IF(B7=0,"",REPT("▓",MIN(20,INT(C7/B7*20)))&REPT("░",MAX(0,20-MIN(20,INT(C7/B7*20))))) | G7: =IF(C7=0,"⬜",IF(C7/B7<0.8,"🟢",IF(C7/B7<=1,"🟡","🔴")))
A8: Total Revenus | B8: =SUM(B4:B7) | C8: =SUM(C4:C7) | D8: =SUM(D4:D7) | E8: =IF(B8=0,0,C8/B8) | F8: =IF(B8=0,"",REPT("▓",MIN(20,INT(C8/B8*20)))&REPT("░",MAX(0,20-MIN(20,INT(C8/B8*20)))))
A10: 🏠 DÉPENSES FIXES
A11: Loyer / Crédit immo | B11: 0 | C11: 0 | D11: =B11-C11 | E11: =IF(B11=0,"—",C11/B11) | F11: =IF(B11=0,"",REPT("▓",MIN(20,INT(C11/B11*20)))&REPT("░",MAX(0,20-MIN(20,INT(C11/B11*20))))) | G11: =IF(C11=0,"⬜",IF(C11/B11<0.8,"🟢",IF(C11/B11<=1,"🟡","🔴")))
A12: Assurances | B12: 0 | C12: 0 | D12: =B12-C12 | E12: =IF(B12=0,"—",C12/B12) | F12: =IF(B12=0,"",REPT("▓",MIN(20,INT(C12/B12*20)))&REPT("░",MAX(0,20-MIN(20,INT(C12/B12*20))))) | G12: =IF(C12=0,"⬜",IF(C12/B12<0.8,"🟢",IF(C12/B12<=1,"🟡","🔴")))
A13: Abonnements | B13: 0 | C13: 0 | D13: =B13-C13 | E13: =IF(B13=0,"—",C13/B13) | F13: =IF(B13=0,"",REPT("▓",MIN(20,INT(C13/B13*20)))&REPT("░",MAX(0,20-MIN(20,INT(C13/B13*20))))) | G13: =IF(C13=0,"⬜",IF(C13/B13<0.8,"🟢",IF(C13/B13<=1,"🟡","🔴")))
A14: Téléphone / Internet | B14: 0 | C14: 0 | D14: =B14-C14 | E14: =IF(B14=0,"—",C14/B14) | F14: =IF(B14=0,"",REPT("▓",MIN(20,INT(C14/B14*20)))&REPT("░",MAX(0,20-MIN(20,INT(C14/B14*20))))) | G14: =IF(C14=0,"⬜",IF(C14/B14<0.8,"🟢",IF(C14/B14<=1,"🟡","🔴")))
A15: Total Fixes | B15: =SUM(B11:B14) | C15: =SUM(C11:C14) | D15: =SUM(D11:D14) | E15: =IF(B15=0,0,C15/B15) | F15: =IF(B15=0,"",REPT("▓",MIN(20,INT(C15/B15*20)))&REPT("░",MAX(0,20-MIN(20,INT(C15/B15*20)))))
A17: 🛒 DÉPENSES VARIABLES
A18: Alimentation | B18: 0 | C18: 0 | D18: =B18-C18 | E18: =IF(B18=0,"—",C18/B18) | F18: =IF(B18=0,"",REPT("▓",MIN(20,INT(C18/B18*20)))&REPT("░",MAX(0,20-MIN(20,INT(C18/B18*20))))) | G18: =IF(C18=0,"⬜",IF(C18/B18<0.8,"🟢",IF(C18/B18<=1,"🟡","🔴")))
A19: Transport | B19: 0 | C19: 0 | D19: =B19-C19 | E19: =IF(B19=0,"—",C19/B19) | F19: =IF(B19=0,"",REPT("▓",MIN(20,INT(C19/B19*20)))&REPT("░",MAX(0,20-MIN(20,INT(C19/B19*20))))) | G19: =IF(C19=0,"⬜",IF(C19/B19<0.8,"🟢",IF(C19/B19<=1,"🟡","🔴")))
A20: Santé | B20: 0 | C20: 0 | D20: =B20-C20 | E20: =IF(B20=0,"—",C20/B20) | F20: =IF(B20=0,"",REPT("▓",MIN(20,INT(C20/B20*20)))&REPT("░",MAX(0,20-MIN(20,INT(C20/B20*20))))) | G20: =IF(C20=0,"⬜",IF(C20/B20<0.8,"🟢",IF(C20/B20<=1,"🟡","🔴")))
A21: Loisirs | B21: 0 | C21: 0 | D21: =B21-C21 | E21: =IF(B21=0,"—",C21/B21) | F21: =IF(B21=0,"",REPT("▓",MIN(20,INT(C21/B21*20)))&REPT("░",MAX(0,20-MIN(20,INT(C21/B21*20))))) | G21: =IF(C21=0,"⬜",IF(C21/B21<0.8,"🟢",IF(C21/B21<=1,"🟡","🔴")))
A22: Shopping | B22: 0 | C22: 0 | D22: =B22-C22 | E22: =IF(B22=0,"—",C22/B22) | F22: =IF(B22=0,"",REPT("▓",MIN(20,INT(C22/B22*20)))&REPT("░",MAX(0,20-MIN(20,INT(C22/B22*20))))) | G22: =IF(C22=0,"⬜",IF(C22/B22<0.8,"🟢",IF(C22/B22<=1,"🟡","🔴")))
A23: Restaurant | B23: 0 | C23: 0 | D23: =B23-C23 | E23: =IF(B23=0,"—",C23/B23) | F23: =IF(B23=0,"",REPT("▓",MIN(20,INT(C23/B23*20)))&REPT("░",MAX(0,20-MIN(20,INT(C23/B23*20))))) | G23: =IF(C23=0,"⬜",IF(C23/B23<0.8,"🟢",IF(C23/B23<=1,"🟡","🔴")))
A24: Beauté | B24: 0 | C24: 0 | D24: =B24-C24 | E24: =IF(B24=0,"—",C24/B24) | F24: =IF(B24=0,"",REPT("▓",MIN(20,INT(C24/B24*20)))&REPT("░",MAX(0,20-MIN(20,INT(C24/B24*20))))) | G24: =IF(C24=0,"⬜",IF(C24/B24<0.8,"🟢",IF(C24/B24<=1,"🟡","🔴")))
A25: Autre | B25: 0 | C25: 0 | D25: =B25-C25 | E25: =IF(B25=0,"—",C25/B25) | F25: =IF(B25=0,"",REPT("▓",MIN(20,INT(C25/B25*20)))&REPT("░",MAX(0,20-MIN(20,INT(C25/B25*20))))) | G25: =IF(C25=0,"⬜",IF(C25/B25<0.8,"🟢",IF(C25/B25<=1,"🟡","🔴")))
A26: Total Variables | B26: =SUM(B18:B25) | C26: =SUM(C18:C25) | D26: =SUM(D18:D25) | E26: =IF(B26=0,0,C26/B26) | F26: =IF(B26=0,"",REPT("▓",MIN(20,INT(C26/B26*20)))&REPT("░",MAX(0,20-MIN(20,INT(C26/B26*20)))))
A28: 💳 CRÉDITS
A29: Crédit auto | B29: 0 | C29: 0 | D29: =B29-C29 | E29: =IF(B29=0,"—",C29/B29) | F29: =IF(B29=0,"",REPT("▓",MIN(20,INT(C29/B29*20)))&REPT("░",MAX(0,20-MIN(20,INT(C29/B29*20))))) | G29: =IF(C29=0,"⬜",IF(C29/B29<0.8,"🟢",IF(C29/B29<=1,"🟡","🔴")))
A30: Crédit conso | B30: 0 | C30: 0 | D30: =B30-C30 | E30: =IF(B30=0,"—",C30/B30) | F30: =IF(B30=0,"",REPT("▓",MIN(20,INT(C30/B30*20)))&REPT("░",MAX(0,20-MIN(20,INT(C30/B30*20))))) | G30: =IF(C30=0,"⬜",IF(C30/B30<0.8,"🟢",IF(C30/B30<=1,"🟡","🔴")))
A31: Autre crédit | B31: 0 | C31: 0 | D31: =B31-C31 | E31: =IF(B31=0,"—",C31/B31) | F31: =IF(B31=0,"",REPT("▓",MIN(20,INT(C31/B31*20)))&REPT("░",MAX(0,20-MIN(20,INT(C31/B31*20))))) | G31: =IF(C31=0,"⬜",IF(C31/B31<0.8,"🟢",IF(C31/B31<=1,"🟡","🔴")))
A32: Total Crédits | B32: =SUM(B29:B31) | C32: =SUM(C29:C31) | D32: =SUM(D29:D31) | E32: =IF(B32=0,0,C32/B32) | F32: =IF(B32=0,"",REPT("▓",MIN(20,INT(C32/B32*20)))&REPT("░",MAX(0,20-MIN(20,INT(C32/B32*20)))))
A34: 🏦 ÉPARGNE
A35: Livret A | B35: 0 | C35: 0 | D35: =B35-C35 | E35: =IF(B35=0,"—",C35/B35) | F35: =IF(B35=0,"",REPT("▓",MIN(20,INT(C35/B35*20)))&REPT("░",MAX(0,20-MIN(20,INT(C35/B35*20))))) | G35: =IF(C35=0,"⬜",IF(C35/B35<0.8,"🟢",IF(C35/B35<=1,"🟡","🔴")))
A36: PEL / CEL | B36: 0 | C36: 0 | D36: =B36-C36 | E36: =IF(B36=0,"—",C36/B36) | F36: =IF(B36=0,"",REPT("▓",MIN(20,INT(C36/B36*20)))&REPT("░",MAX(0,20-MIN(20,INT(C36/B36*20))))) | G36: =IF(C36=0,"⬜",IF(C36/B36<0.8,"🟢",IF(C36/B36<=1,"🟡","🔴")))
A37: Assurance-vie | B37: 0 | C37: 0 | D37: =B37-C37 | E37: =IF(B37=0,"—",C37/B37) | F37: =IF(B37=0,"",REPT("▓",MIN(20,INT(C37/B37*20)))&REPT("░",MAX(0,20-MIN(20,INT(C37/B37*20))))) | G37: =IF(C37=0,"⬜",IF(C37/B37<0.8,"🟢",IF(C37/B37<=1,"🟡","🔴")))
A38: Investissements | B38: 0 | C38: 0 | D38: =B38-C38 | E38: =IF(B38=0,"—",C38/B38) | F38: =IF(B38=0,"",REPT("▓",MIN(20,INT(C38/B38*20)))&REPT("░",MAX(0,20-MIN(20,INT(C38/B38*20))))) | G38: =IF(C38=0,"⬜",IF(C38/B38<0.8,"🟢",IF(C38/B38<=1,"🟡","🔴")))
A39: Total Épargne | B39: =SUM(B35:B38) | C39: =SUM(C35:C38) | D39: =SUM(D35:D38) | E39: =IF(B39=0,0,C39/B39) | F39: =IF(B39=0,"",REPT("▓",MIN(20,INT(C39/B39*20)))&REPT("░",MAX(0,20-MIN(20,INT(C39/B39*20)))))
A42: ✦ BILAN DU MOIS
A43: 💰 Total Revenus | F43: =C8
A44: 💸 Total Dépenses | F44: =C15+C26+C32
A45: 📊 Solde du mois | F45: =C8-(C15+C26+C32)
A46: 🎯 Taux d'épargne | F46: =IF(C8=0,0,(C8-(C15+C26+C32))/C8)
A47: 🏦 Épargne réelle | F47: =C39

Sheet Mars
A1: ✦ MARS ✦
A2: Catégorie | B2: Budget prévu | C2: Réel dépensé | D2: Écart | E2: % utilisé | F2: Progression
A3: 💰 REVENUS
A4: Salaire net | B4: 0 | C4: 0 | D4: =B4-C4 | E4: =IF(B4=0,"—",C4/B4) | F4: =IF(B4=0,"",REPT("▓",MIN(20,INT(C4/B4*20)))&REPT("░",MAX(0,20-MIN(20,INT(C4/B4*20))))) | G4: =IF(C4=0,"⬜",IF(C4/B4<0.8,"🟢",IF(C4/B4<=1,"🟡","🔴")))
A5: Freelance / Side | B5: 0 | C5: 0 | D5: =B5-C5 | E5: =IF(B5=0,"—",C5/B5) | F5: =IF(B5=0,"",REPT("▓",MIN(20,INT(C5/B5*20)))&REPT("░",MAX(0,20-MIN(20,INT(C5/B5*20))))) | G5: =IF(C5=0,"⬜",IF(C5/B5<0.8,"🟢",IF(C5/B5<=1,"🟡","🔴")))
A6: Aides / APL | B6: 0 | C6: 0 | D6: =B6-C6 | E6: =IF(B6=0,"—",C6/B6) | F6: =IF(B6=0,"",REPT("▓",MIN(20,INT(C6/B6*20)))&REPT("░",MAX(0,20-MIN(20,INT(C6/B6*20))))) | G6: =IF(C6=0,"⬜",IF(C6/B6<0.8,"🟢",IF(C6/B6<=1,"🟡","🔴")))
A7: Autres revenus | B7: 0 | C7: 0 | D7: =B7-C7 | E7: =IF(B7=0,"—",C7/B7) | F7: =IF(B7=0,"",REPT("▓",MIN(20,INT(C7/B7*20)))&REPT("░",MAX(0,20-MIN(20,INT(C7/B7*20))))) | G7: =IF(C7=0,"⬜",IF(C7/B7<0.8,"🟢",IF(C7/B7<=1,"🟡","🔴")))
A8: Total Revenus | B8: =SUM(B4:B7) | C8: =SUM(C4:C7) | D8: =SUM(D4:D7) | E8: =IF(B8=0,0,C8/B8) | F8: =IF(B8=0,"",REPT("▓",MIN(20,INT(C8/B8*20)))&REPT("░",MAX(0,20-MIN(20,INT(C8/B8*20)))))
A10: 🏠 DÉPENSES FIXES
A11: Loyer / Crédit immo | B11: 0 | C11: 0 | D11: =B11-C11 | E11: =IF(B11=0,"—",C11/B11) | F11: =IF(B11=0,"",REPT("▓",MIN(20,INT(C11/B11*20)))&REPT("░",MAX(0,20-MIN(20,INT(C11/B11*20))))) | G11: =IF(C11=0,"⬜",IF(C11/B11<0.8,"🟢",IF(C11/B11<=1,"🟡","🔴")))
A12: Assurances | B12: 0 | C12: 0 | D12: =B12-C12 | E12: =IF(B12=0,"—",C12/B12) | F12: =IF(B12=0,"",REPT("▓",MIN(20,INT(C12/B12*20)))&REPT("░",MAX(0,20-MIN(20,INT(C12/B12*20))))) | G12: =IF(C12=0,"⬜",IF(C12/B12<0.8,"🟢",IF(C12/B12<=1,"🟡","🔴")))
A13: Abonnements | B13: 0 | C13: 0 | D13: =B13-C13 | E13: =IF(B13=0,"—",C13/B13) | F13: =IF(B13=0,"",REPT("▓",MIN(20,INT(C13/B13*20)))&REPT("░",MAX(0,20-MIN(20,INT(C13/B13*20))))) | G13: =IF(C13=0,"⬜",IF(C13/B13<0.8,"🟢",IF(C13/B13<=1,"🟡","🔴")))
A14: Téléphone / Internet | B14: 0 | C14: 0 | D14: =B14-C14 | E14: =IF(B14=0,"—",C14/B14) | F14: =IF(B14=0,"",REPT("▓",MIN(20,INT(C14/B14*20)))&REPT("░",MAX(0,20-MIN(20,INT(C14/B14*20))))) | G14: =IF(C14=0,"⬜",IF(C14/B14<0.8,"🟢",IF(C14/B14<=1,"🟡","🔴")))
A15: Total Fixes | B15: =SUM(B11:B14) | C15: =SUM(C11:C14) | D15: =SUM(D11:D14) | E15: =IF(B15=0,0,C15/B15) | F15: =IF(B15=0,"",REPT("▓",MIN(20,INT(C15/B15*20)))&REPT("░",MAX(0,20-MIN(20,INT(C15/B15*20)))))
A17: 🛒 DÉPENSES VARIABLES
A18: Alimentation | B18: 0 | C18: 0 | D18: =B18-C18 | E18: =IF(B18=0,"—",C18/B18) | F18: =IF(B18=0,"",REPT("▓",MIN(20,INT(C18/B18*20)))&REPT("░",MAX(0,20-MIN(20,INT(C18/B18*20))))) | G18: =IF(C18=0,"⬜",IF(C18/B18<0.8,"🟢",IF(C18/B18<=1,"🟡","🔴")))
A19: Transport | B19: 0 | C19: 0 | D19: =B19-C19 | E19: =IF(B19=0,"—",C19/B19) | F19: =IF(B19=0,"",REPT("▓",MIN(20,INT(C19/B19*20)))&REPT("░",MAX(0,20-MIN(20,INT(C19/B19*20))))) | G19: =IF(C19=0,"⬜",IF(C19/B19<0.8,"🟢",IF(C19/B19<=1,"🟡","🔴")))
A20: Santé | B20: 0 | C20: 0 | D20: =B20-C20 | E20: =IF(B20=0,"—",C20/B20) | F20: =IF(B20=0,"",REPT("▓",MIN(20,INT(C20/B20*20)))&REPT("░",MAX(0,20-MIN(20,INT(C20/B20*20))))) | G20: =IF(C20=0,"⬜",IF(C20/B20<0.8,"🟢",IF(C20/B20<=1,"🟡","🔴")))
A21: Loisirs | B21: 0 | C21: 0 | D21: =B21-C21 | E21: =IF(B21=0,"—",C21/B21) | F21: =IF(B21=0,"",REPT("▓",MIN(20,INT(C21/B21*20)))&REPT("░",MAX(0,20-MIN(20,INT(C21/B21*20))))) | G21: =IF(C21=0,"⬜",IF(C21/B21<0.8,"🟢",IF(C21/B21<=1,"🟡","🔴")))
A22: Shopping | B22: 0 | C22: 0 | D22: =B22-C22 | E22: =IF(B22=0,"—",C22/B22) | F22: =IF(B22=0,"",REPT("▓",MIN(20,INT(C22/B22*20)))&REPT("░",MAX(0,20-MIN(20,INT(C22/B22*20))))) | G22: =IF(C22=0,"⬜",IF(C22/B22<0.8,"🟢",IF(C22/B22<=1,"🟡","🔴")))
A23: Restaurant | B23: 0 | C23: 0 | D23: =B23-C23 | E23: =IF(B23=0,"—",C23/B23) | F23: =IF(B23=0,"",REPT("▓",MIN(20,INT(C23/B23*20)))&REPT("░",MAX(0,20-MIN(20,INT(C23/B23*20))))) | G23: =IF(C23=0,"⬜",IF(C23/B23<0.8,"🟢",IF(C23/B23<=1,"🟡","🔴")))
A24: Beauté | B24: 0 | C24: 0 | D24: =B24-C24 | E24: =IF(B24=0,"—",C24/B24) | F24: =IF(B24=0,"",REPT("▓",MIN(20,INT(C24/B24*20)))&REPT("░",MAX(0,20-MIN(20,INT(C24/B24*20))))) | G24: =IF(C24=0,"⬜",IF(C24/B24<0.8,"🟢",IF(C24/B24<=1,"🟡","🔴")))
A25: Autre | B25: 0 | C25: 0 | D25: =B25-C25 | E25: =IF(B25=0,"—",C25/B25) | F25: =IF(B25=0,"",REPT("▓",MIN(20,INT(C25/B25*20)))&REPT("░",MAX(0,20-MIN(20,INT(C25/B25*20))))) | G25: =IF(C25=0,"⬜",IF(C25/B25<0.8,"🟢",IF(C25/B25<=1,"🟡","🔴")))
A26: Total Variables | B26: =SUM(B18:B25) | C26: =SUM(C18:C25) | D26: =SUM(D18:D25) | E26: =IF(B26=0,0,C26/B26) | F26: =IF(B26=0,"",REPT("▓",MIN(20,INT(C26/B26*20)))&REPT("░",MAX(0,20-MIN(20,INT(C26/B26*20)))))
A28: 💳 CRÉDITS
A29: Crédit auto | B29: 0 | C29: 0 | D29: =B29-C29 | E29: =IF(B29=0,"—",C29/B29) | F29: =IF(B29=0,"",REPT("▓",MIN(20,INT(C29/B29*20)))&REPT("░",MAX(0,20-MIN(20,INT(C29/B29*20))))) | G29: =IF(C29=0,"⬜",IF(C29/B29<0.8,"🟢",IF(C29/B29<=1,"🟡","🔴")))
A30: Crédit conso | B30: 0 | C30: 0 | D30: =B30-C30 | E30: =IF(B30=0,"—",C30/B30) | F30: =IF(B30=0,"",REPT("▓",MIN(20,INT(C30/B30*20)))&REPT("░",MAX(0,20-MIN(20,INT(C30/B30*20))))) | G30: =IF(C30=0,"⬜",IF(C30/B30<0.8,"🟢",IF(C30/B30<=1,"🟡","🔴")))
A31: Autre crédit | B31: 0 | C31: 0 | D31: =B31-C31 | E31: =IF(B31=0,"—",C31/B31) | F31: =IF(B31=0,"",REPT("▓",MIN(20,INT(C31/B31*20)))&REPT("░",MAX(0,20-MIN(20,INT(C31/B31*20))))) | G31: =IF(C31=0,"⬜",IF(C31/B31<0.8,"🟢",IF(C31/B31<=1,"🟡","🔴")))
A32: Total Crédits | B32: =SUM(B29:B31) | C32: =SUM(C29:C31) | D32: =SUM(D29:D31) | E32: =IF(B32=0,0,C32/B32) | F32: =IF(B32=0,"",REPT("▓",MIN(20,INT(C32/B32*20)))&REPT("░",MAX(0,20-MIN(20,INT(C32/B32*20)))))
A34: 🏦 ÉPARGNE
A35: Livret A | B35: 0 | C35: 0 | D35: =B35-C35 | E35: =IF(B35=0,"—",C35/B35) | F35: =IF(B35=0,"",REPT("▓",MIN(20,INT(C35/B35*20)))&REPT("░",MAX(0,20-MIN(20,INT(C35/B35*20))))) | G35: =IF(C35=0,"⬜",IF(C35/B35<0.8,"🟢",IF(C35/B35<=1,"🟡","🔴")))
A36: PEL / CEL | B36: 0 | C36: 0 | D36: =B36-C36 | E36: =IF(B36=0,"—",C36/B36) | F36: =IF(B36=0,"",REPT("▓",MIN(20,INT(C36/B36*20)))&REPT("░",MAX(0,20-MIN(20,INT(C36/B36*20))))) | G36: =IF(C36=0,"⬜",IF(C36/B36<0.8,"🟢",IF(C36/B36<=1,"🟡","🔴")))
A37: Assurance-vie | B37: 0 | C37: 0 | D37: =B37-C37 | E37: =IF(B37=0,"—",C37/B37) | F37: =IF(B37=0,"",REPT("▓",MIN(20,INT(C37/B37*20)))&REPT("░",MAX(0,20-MIN(20,INT(C37/B37*20))))) | G37: =IF(C37=0,"⬜",IF(C37/B37<0.8,"🟢",IF(C37/B37<=1,"🟡","🔴")))
A38: Investissements | B38: 0 | C38: 0 | D38: =B38-C38 | E38: =IF(B38=0,"—",C38/B38) | F38: =IF(B38=0,"",REPT("▓",MIN(20,INT(C38/B38*20)))&REPT("░",MAX(0,20-MIN(20,INT(C38/B38*20))))) | G38: =IF(C38=0,"⬜",IF(C38/B38<0.8,"🟢",IF(C38/B38<=1,"🟡","🔴")))
A39: Total Épargne | B39: =SUM(B35:B38) | C39: =SUM(C35:C38) | D39: =SUM(D35:D38) | E39: =IF(B39=0,0,C39/B39) | F39: =IF(B39=0,"",REPT("▓",MIN(20,INT(C39/B39*20)))&REPT("░",MAX(0,20-MIN(20,INT(C39/B39*20)))))
A42: ✦ BILAN DU MOIS
A43: 💰 Total Revenus | F43: =C8
A44: 💸 Total Dépenses | F44: =C15+C26+C32
A45: 📊 Solde du mois | F45: =C8-(C15+C26+C32)
A46: 🎯 Taux d'épargne | F46: =IF(C8=0,0,(C8-(C15+C26+C32))/C8)
A47: 🏦 Épargne réelle | F47: =C39

Sheet Avril
A1: ✦ AVRIL ✦
A2: Catégorie | B2: Budget prévu | C2: Réel dépensé | D2: Écart | E2: % utilisé | F2: Progression
A3: 💰 REVENUS
A4: Salaire net | B4: 0 | C4: 0 | D4: =B4-C4 | E4: =IF(B4=0,"—",C4/B4) | F4: =IF(B4=0,"",REPT("▓",MIN(20,INT(C4/B4*20)))&REPT("░",MAX(0,20-MIN(20,INT(C4/B4*20))))) | G4: =IF(C4=0,"⬜",IF(C4/B4<0.8,"🟢",IF(C4/B4<=1,"🟡","🔴")))
A5: Freelance / Side | B5: 0 | C5: 0 | D5: =B5-C5 | E5: =IF(B5=0,"—",C5/B5) | F5: =IF(B5=0,"",REPT("▓",MIN(20,INT(C5/B5*20)))&REPT("░",MAX(0,20-MIN(20,INT(C5/B5*20))))) | G5: =IF(C5=0,"⬜",IF(C5/B5<0.8,"🟢",IF(C5/B5<=1,"🟡","🔴")))
A6: Aides / APL | B6: 0 | C6: 0 | D6: =B6-C6 | E6: =IF(B6=0,"—",C6/B6) | F6: =IF(B6=0,"",REPT("▓",MIN(20,INT(C6/B6*20)))&REPT("░",MAX(0,20-MIN(20,INT(C6/B6*20))))) | G6: =IF(C6=0,"⬜",IF(C6/B6<0.8,"🟢",IF(C6/B6<=1,"🟡","🔴")))
A7: Autres revenus | B7: 0 | C7: 0 | D7: =B7-C7 | E7: =IF(B7=0,"—",C7/B7) | F7: =IF(B7=0,"",REPT("▓",MIN(20,INT(C7/B7*20)))&REPT("░",MAX(0,20-MIN(20,INT(C7/B7*20))))) | G7: =IF(C7=0,"⬜",IF(C7/B7<0.8,"🟢",IF(C7/B7<=1,"🟡","🔴")))
A8: Total Revenus | B8: =SUM(B4:B7) | C8: =SUM(C4:C7) | D8: =SUM(D4:D7) | E8: =IF(B8=0,0,C8/B8) | F8: =IF(B8=0,"",REPT("▓",MIN(20,INT(C8/B8*20)))&REPT("░",MAX(0,20-MIN(20,INT(C8/B8*20)))))
A10: 🏠 DÉPENSES FIXES
A11: Loyer / Crédit immo | B11: 0 | C11: 0 | D11: =B11-C11 | E11: =IF(B11=0,"—",C11/B11) | F11: =IF(B11=0,"",REPT("▓",MIN(20,INT(C11/B11*20)))&REPT("░",MAX(0,20-MIN(20,INT(C11/B11*20))))) | G11: =IF(C11=0,"⬜",IF(C11/B11<0.8,"🟢",IF(C11/B11<=1,"🟡","🔴")))
A12: Assurances | B12: 0 | C12: 0 | D12: =B12-C12 | E12: =IF(B12=0,"—",C12/B12) | F12: =IF(B12=0,"",REPT("▓",MIN(20,INT(C12/B12*20)))&REPT("░",MAX(0,20-MIN(20,INT(C12/B12*20))))) | G12: =IF(C12=0,"⬜",IF(C12/B12<0.8,"🟢",IF(C12/B12<=1,"🟡","🔴")))
A13: Abonnements | B13: 0 | C13: 0 | D13: =B13-C13 | E13: =IF(B13=0,"—",C13/B13) | F13: =IF(B13=0,"",REPT("▓",MIN(20,INT(C13/B13*20)))&REPT("░",MAX(0,20-MIN(20,INT(C13/B13*20))))) | G13: =IF(C13=0,"⬜",IF(C13/B13<0.8,"🟢",IF(C13/B13<=1,"🟡","🔴")))
A14: Téléphone / Internet | B14: 0 | C14: 0 | D14: =B14-C14 | E14: =IF(B14=0,"—",C14/B14) | F14: =IF(B14=0,"",REPT("▓",MIN(20,INT(C14/B14*20)))&REPT("░",MAX(0,20-MIN(20,INT(C14/B14*20))))) | G14: =IF(C14=0,"⬜",IF(C14/B14<0.8,"🟢",IF(C14/B14<=1,"🟡","🔴")))
A15: Total Fixes | B15: =SUM(B11:B14) | C15: =SUM(C11:C14) | D15: =SUM(D11:D14) | E15: =IF(B15=0,0,C15/B15) | F15: =IF(B15=0,"",REPT("▓",MIN(20,INT(C15/B15*20)))&REPT("░",MAX(0,20-MIN(20,INT(C15/B15*20)))))
A17: 🛒 DÉPENSES VARIABLES
A18: Alimentation | B18: 0 | C18: 0 | D18: =B18-C18 | E18: =IF(B18=0,"—",C18/B18) | F18: =IF(B18=0,"",REPT("▓",MIN(20,INT(C18/B18*20)))&REPT("░",MAX(0,20-MIN(20,INT(C18/B18*20))))) | G18: =IF(C18=0,"⬜",IF(C18/B18<0.8,"🟢",IF(C18/B18<=1,"🟡","🔴")))
A19: Transport | B19: 0 | C19: 0 | D19: =B19-C19 | E19: =IF(B19=0,"—",C19/B19) | F19: =IF(B19=0,"",REPT("▓",MIN(20,INT(C19/B19*20)))&REPT("░",MAX(0,20-MIN(20,INT(C19/B19*20))))) | G19: =IF(C19=0,"⬜",IF(C19/B19<0.8,"🟢",IF(C19/B19<=1,"🟡","🔴")))
A20: Santé | B20: 0 | C20: 0 | D20: =B20-C20 | E20: =IF(B20=0,"—",C20/B20) | F20: =IF(B20=0,"",REPT("▓",MIN(20,INT(C20/B20*20)))&REPT("░",MAX(0,20-MIN(20,INT(C20/B20*20))))) | G20: =IF(C20=0,"⬜",IF(C20/B20<0.8,"🟢",IF(C20/B20<=1,"🟡","🔴")))
A21: Loisirs | B21: 0 | C21: 0 | D21: =B21-C21 | E21: =IF(B21=0,"—",C21/B21) | F21: =IF(B21=0,"",REPT("▓",MIN(20,INT(C21/B21*20)))&REPT("░",MAX(0,20-MIN(20,INT(C21/B21*20))))) | G21: =IF(C21=0,"⬜",IF(C21/B21<0.8,"🟢",IF(C21/B21<=1,"🟡","🔴")))
A22: Shopping | B22: 0 | C22: 0 | D22: =B22-C22 | E22: =IF(B22=0,"—",C22/B22) | F22: =IF(B22=0,"",REPT("▓",MIN(20,INT(C22/B22*20)))&REPT("░",MAX(0,20-MIN(20,INT(C22/B22*20))))) | G22: =IF(C22=0,"⬜",IF(C22/B22<0.8,"🟢",IF(C22/B22<=1,"🟡","🔴")))
A23: Restaurant | B23: 0 | C23: 0 | D23: =B23-C23 | E23: =IF(B23=0,"—",C23/B23) | F23: =IF(B23=0,"",REPT("▓",MIN(20,INT(C23/B23*20)))&REPT("░",MAX(0,20-MIN(20,INT(C23/B23*20))))) | G23: =IF(C23=0,"⬜",IF(C23/B23<0.8,"🟢",IF(C23/B23<=1,"🟡","🔴")))
A24: Beauté | B24: 0 | C24: 0 | D24: =B24-C24 | E24: =IF(B24=0,"—",C24/B24) | F24: =IF(B24=0,"",REPT("▓",MIN(20,INT(C24/B24*20)))&REPT("░",MAX(0,20-MIN(20,INT(C24/B24*20))))) | G24: =IF(C24=0,"⬜",IF(C24/B24<0.8,"🟢",IF(C24/B24<=1,"🟡","🔴")))
A25: Autre | B25: 0 | C25: 0 | D25: =B25-C25 | E25: =IF(B25=0,"—",C25/B25) | F25: =IF(B25=0,"",REPT("▓",MIN(20,INT(C25/B25*20)))&REPT("░",MAX(0,20-MIN(20,INT(C25/B25*20))))) | G25: =IF(C25=0,"⬜",IF(C25/B25<0.8,"🟢",IF(C25/B25<=1,"🟡","🔴")))
A26: Total Variables | B26: =SUM(B18:B25) | C26: =SUM(C18:C25) | D26: =SUM(D18:D25) | E26: =IF(B26=0,0,C26/B26) | F26: =IF(B26=0,"",REPT("▓",MIN(20,INT(C26/B26*20)))&REPT("░",MAX(0,20-MIN(20,INT(C26/B26*20)))))
A28: 💳 CRÉDITS
A29: Crédit auto | B29: 0 | C29: 0 | D29: =B29-C29 | E29: =IF(B29=0,"—",C29/B29) | F29: =IF(B29=0,"",REPT("▓",MIN(20,INT(C29/B29*20)))&REPT("░",MAX(0,20-MIN(20,INT(C29/B29*20))))) | G29: =IF(C29=0,"⬜",IF(C29/B29<0.8,"🟢",IF(C29/B29<=1,"🟡","🔴")))
A30: Crédit conso | B30: 0 | C30: 0 | D30: =B30-C30 | E30: =IF(B30=0,"—",C30/B30) | F30: =IF(B30=0,"",REPT("▓",MIN(20,INT(C30/B30*20)))&REPT("░",MAX(0,20-MIN(20,INT(C30/B30*20))))) | G30: =IF(C30=0,"⬜",IF(C30/B30<0.8,"🟢",IF(C30/B30<=1,"🟡","🔴")))
A31: Autre crédit | B31: 0 | C31: 0 | D31: =B31-C31 | E31: =IF(B31=0,"—",C31/B31) | F31: =IF(B31=0,"",REPT("▓",MIN(20,INT(C31/B31*20)))&REPT("░",MAX(0,20-MIN(20,INT(C31/B31*20))))) | G31: =IF(C31=0,"⬜",IF(C31/B31<0.8,"🟢",IF(C31/B31<=1,"🟡","🔴")))
A32: Total Crédits | B32: =SUM(B29:B31) | C32: =SUM(C29:C31) | D32: =SUM(D29:D31) | E32: =IF(B32=0,0,C32/B32) | F32: =IF(B32=0,"",REPT("▓",MIN(20,INT(C32/B32*20)))&REPT("░",MAX(0,20-MIN(20,INT(C32/B32*20)))))
A34: 🏦 ÉPARGNE
A35: Livret A | B35: 0 | C35: 0 | D35: =B35-C35 | E35: =IF(B35=0,"—",C35/B35) | F35: =IF(B35=0,"",REPT("▓",MIN(20,INT(C35/B35*20)))&REPT("░",MAX(0,20-MIN(20,INT(C35/B35*20))))) | G35: =IF(C35=0,"⬜",IF(C35/B35<0.8,"🟢",IF(C35/B35<=1,"🟡","🔴")))
A36: PEL / CEL | B36: 0 | C36: 0 | D36: =B36-C36 | E36: =IF(B36=0,"—",C36/B36) | F36: =IF(B36=0,"",REPT("▓",MIN(20,INT(C36/B36*20)))&REPT("░",MAX(0,20-MIN(20,INT(C36/B36*20))))) | G36: =IF(C36=0,"⬜",IF(C36/B36<0.8,"🟢",IF(C36/B36<=1,"🟡","🔴")))
A37: Assurance-vie | B37: 0 | C37: 0 | D37: =B37-C37 | E37: =IF(B37=0,"—",C37/B37) | F37: =IF(B37=0,"",REPT("▓",MIN(20,INT(C37/B37*20)))&REPT("░",MAX(0,20-MIN(20,INT(C37/B37*20))))) | G37: =IF(C37=0,"⬜",IF(C37/B37<0.8,"🟢",IF(C37/B37<=1,"🟡","🔴")))
A38: Investissements | B38: 0 | C38: 0 | D38: =B38-C38 | E38: =IF(B38=0,"—",C38/B38) | F38: =IF(B38=0,"",REPT("▓",MIN(20,INT(C38/B38*20)))&REPT("░",MAX(0,20-MIN(20,INT(C38/B38*20))))) | G38: =IF(C38=0,"⬜",IF(C38/B38<0.8,"🟢",IF(C38/B38<=1,"🟡","🔴")))
A39: Total Épargne | B39: =SUM(B35:B38) | C39: =SUM(C35:C38) | D39: =SUM(D35:D38) | E39: =IF(B39=0,0,C39/B39) | F39: =IF(B39=0,"",REPT("▓",MIN(20,INT(C39/B39*20)))&REPT("░",MAX(0,20-MIN(20,INT(C39/B39*20)))))
A42: ✦ BILAN DU MOIS
A43: 💰 Total Revenus | F43: =C8
A44: 💸 Total Dépenses | F44: =C15+C26+C32
A45: 📊 Solde du mois | F45: =C8-(C15+C26+C32)
A46: 🎯 Taux d'épargne | F46: =IF(C8=0,0,(C8-(C15+C26+C32))/C8)
A47: 🏦 Épargne réelle | F47: =C39

Sheet Mai
A1: ✦ MAI ✦
A2: Catégorie | B2: Budget prévu | C2: Réel dépensé | D2: Écart | E2: % utilisé | F2: Progression
A3: 💰 REVENUS
A4: Salaire net | B4: 0 | C4: 0 | D4: =B4-C4 | E4: =IF(B4=0,"—",C4/B4) | F4: =IF(B4=0,"",REPT("▓",MIN(20,INT(C4/B4*20)))&REPT("░",MAX(0,20-MIN(20,INT(C4/B4*20))))) | G4: =IF(C4=0,"⬜",IF(C4/B4<0.8,"🟢",IF(C4/B4<=1,"🟡","🔴")))
A5: Freelance / Side | B5: 0 | C5: 0 | D5: =B5-C5 | E5: =IF(B5=0,"—",C5/B5) | F5: =IF(B5=0,"",REPT("▓",MIN(20,INT(C5/B5*20)))&REPT("░",MAX(0,20-MIN(20,INT(C5/B5*20))))) | G5: =IF(C5=0,"⬜",IF(C5/B5<0.8,"🟢",IF(C5/B5<=1,"🟡","🔴")))
A6: Aides / APL | B6: 0 | C6: 0 | D6: =B6-C6 | E6: =IF(B6=0,"—",C6/B6) | F6: =IF(B6=0,"",REPT("▓",MIN(20,INT(C6/B6*20)))&REPT("░",MAX(0,20-MIN(20,INT(C6/B6*20))))) | G6: =IF(C6=0,"⬜",IF(C6/B6<0.8,"🟢",IF(C6/B6<=1,"🟡","🔴")))
A7: Autres revenus | B7: 0 | C7: 0 | D7: =B7-C7 | E7: =IF(B7=0,"—",C7/B7) | F7: =IF(B7=0,"",REPT("▓",MIN(20,INT(C7/B7*20)))&REPT("░",MAX(0,20-MIN(20,INT(C7/B7*20))))) | G7: =IF(C7=0,"⬜",IF(C7/B7<0.8,"🟢",IF(C7/B7<=1,"🟡","🔴")))
A8: Total Revenus | B8: =SUM(B4:B7) | C8: =SUM(C4:C7) | D8: =SUM(D4:D7) | E8: =IF(B8=0,0,C8/B8) | F8: =IF(B8=0,"",REPT("▓",MIN(20,INT(C8/B8*20)))&REPT("░",MAX(0,20-MIN(20,INT(C8/B8*20)))))
A10: 🏠 DÉPENSES FIXES
A11: Loyer / Crédit immo | B11: 0 | C11: 0 | D11: =B11-C11 | E11: =IF(B11=0,"—",C11/B11) | F11: =IF(B11=0,"",REPT("▓",MIN(20,INT(C11/B11*20)))&REPT("░",MAX(0,20-MIN(20,INT(C11/B11*20))))) | G11: =IF(C11=0,"⬜",IF(C11/B11<0.8,"🟢",IF(C11/B11<=1,"🟡","🔴")))
A12: Assurances | B12: 0 | C12: 0 | D12: =B12-C12 | E12: =IF(B12=0,"—",C12/B12) | F12: =IF(B12=0,"",REPT("▓",MIN(20,INT(C12/B12*20)))&REPT("░",MAX(0,20-MIN(20,INT(C12/B12*20))))) | G12: =IF(C12=0,"⬜",IF(C12/B12<0.8,"🟢",IF(C12/B12<=1,"🟡","🔴")))
A13: Abonnements | B13: 0 | C13: 0 | D13: =B13-C13 | E13: =IF(B13=0,"—",C13/B13) | F13: =IF(B13=0,"",REPT("▓",MIN(20,INT(C13/B13*20)))&REPT("░",MAX(0,20-MIN(20,INT(C13/B13*20))))) | G13: =IF(C13=0,"⬜",IF(C13/B13<0.8,"🟢",IF(C13/B13<=1,"🟡","🔴")))
A14: Téléphone / Internet | B14: 0 | C14: 0 | D14: =B14-C14 | E14: =IF(B14=0,"—",C14/B14) | F14: =IF(B14=0,"",REPT("▓",MIN(20,INT(C14/B14*20)))&REPT("░",MAX(0,20-MIN(20,INT(C14/B14*20))))) | G14: =IF(C14=0,"⬜",IF(C14/B14<0.8,"🟢",IF(C14/B14<=1,"🟡","🔴")))
A15: Total Fixes | B15: =SUM(B11:B14) | C15: =SUM(C11:C14) | D15: =SUM(D11:D14) | E15: =IF(B15=0,0,C15/B15) | F15: =IF(B15=0,"",REPT("▓",MIN(20,INT(C15/B15*20)))&REPT("░",MAX(0,20-MIN(20,INT(C15/B15*20)))))
A17: 🛒 DÉPENSES VARIABLES
A18: Alimentation | B18: 0 | C18: 0 | D18: =B18-C18 | E18: =IF(B18=0,"—",C18/B18) | F18: =IF(B18=0,"",REPT("▓",MIN(20,INT(C18/B18*20)))&REPT("░",MAX(0,20-MIN(20,INT(C18/B18*20))))) | G18: =IF(C18=0,"⬜",IF(C18/B18<0.8,"🟢",IF(C18/B18<=1,"🟡","🔴")))
A19: Transport | B19: 0 | C19: 0 | D19: =B19-C19 | E19: =IF(B19=0,"—",C19/B19) | F19: =IF(B19=0,"",REPT("▓",MIN(20,INT(C19/B19*20)))&REPT("░",MAX(0,20-MIN(20,INT(C19/B19*20))))) | G19: =IF(C19=0,"⬜",IF(C19/B19<0.8,"🟢",IF(C19/B19<=1,"🟡","🔴")))
A20: Santé | B20: 0 | C20: 0 | D20: =B20-C20 | E20: =IF(B20=0,"—",C20/B20) | F20: =IF(B20=0,"",REPT("▓",MIN(20,INT(C20/B20*20)))&REPT("░",MAX(0,20-MIN(20,INT(C20/B20*20))))) | G20: =IF(C20=0,"⬜",IF(C20/B20<0.8,"🟢",IF(C20/B20<=1,"🟡","🔴")))
A21: Loisirs | B21: 0 | C21: 0 | D21: =B21-C21 | E21: =IF(B21=0,"—",C21/B21) | F21: =IF(B21=0,"",REPT("▓",MIN(20,INT(C21/B21*20)))&REPT("░",MAX(0,20-MIN(20,INT(C21/B21*20))))) | G21: =IF(C21=0,"⬜",IF(C21/B21<0.8,"🟢",IF(C21/B21<=1,"🟡","🔴")))
A22: Shopping | B22: 0 | C22: 0 | D22: =B22-C22 | E22: =IF(B22=0,"—",C22/B22) | F22: =IF(B22=0,"",REPT("▓",MIN(20,INT(C22/B22*20)))&REPT("░",MAX(0,20-MIN(20,INT(C22/B22*20))))) | G22: =IF(C22=0,"⬜",IF(C22/B22<0.8,"🟢",IF(C22/B22<=1,"🟡","🔴")))
A23: Restaurant | B23: 0 | C23: 0 | D23: =B23-C23 | E23: =IF(B23=0,"—",C23/B23) | F23: =IF(B23=0,"",REPT("▓",MIN(20,INT(C23/B23*20)))&REPT("░",MAX(0,20-MIN(20,INT(C23/B23*20))))) | G23: =IF(C23=0,"⬜",IF(C23/B23<0.8,"🟢",IF(C23/B23<=1,"🟡","🔴")))
A24: Beauté | B24: 0 | C24: 0 | D24: =B24-C24 | E24: =IF(B24=0,"—",C24/B24) | F24: =IF(B24=0,"",REPT("▓",MIN(20,INT(C24/B24*20)))&REPT("░",MAX(0,20-MIN(20,INT(C24/B24*20))))) | G24: =IF(C24=0,"⬜",IF(C24/B24<0.8,"🟢",IF(C24/B24<=1,"🟡","🔴")))
A25: Autre | B25: 0 | C25: 0 | D25: =B25-C25 | E25: =IF(B25=0,"—",C25/B25) | F25: =IF(B25=0,"",REPT("▓",MIN(20,INT(C25/B25*20)))&REPT("░",MAX(0,20-MIN(20,INT(C25/B25*20))))) | G25: =IF(C25=0,"⬜",IF(C25/B25<0.8,"🟢",IF(C25/B25<=1,"🟡","🔴")))
A26: Total Variables | B26: =SUM(B18:B25) | C26: =SUM(C18:C25) | D26: =SUM(D18:D25) | E26: =IF(B26=0,0,C26/B26) | F26: =IF(B26=0,"",REPT("▓",MIN(20,INT(C26/B26*20)))&REPT("░",MAX(0,20-MIN(20,INT(C26/B26*20)))))
A28: 💳 CRÉDITS
A29: Crédit auto | B29: 0 | C29: 0 | D29: =B29-C29 | E29: =IF(B29=0,"—",C29/B29) | F29: =IF(B29=0,"",REPT("▓",MIN(20,INT(C29/B29*20)))&REPT("░",MAX(0,20-MIN(20,INT(C29/B29*20))))) | G29: =IF(C29=0,"⬜",IF(C29/B29<0.8,"🟢",IF(C29/B29<=1,"🟡","🔴")))
A30: Crédit conso | B30: 0 | C30: 0 | D30: =B30-C30 | E30: =IF(B30=0,"—",C30/B30) | F30: =IF(B30=0,"",REPT("▓",MIN(20,INT(C30/B30*20)))&REPT("░",MAX(0,20-MIN(20,INT(C30/B30*20))))) | G30: =IF(C30=0,"⬜",IF(C30/B30<0.8,"🟢",IF(C30/B30<=1,"🟡","🔴")))
A31: Autre crédit | B31: 0 | C31: 0 | D31: =B31-C31 | E31: =IF(B31=0,"—",C31/B31) | F31: =IF(B31=0,"",REPT("▓",MIN(20,INT(C31/B31*20)))&REPT("░",MAX(0,20-MIN(20,INT(C31/B31*20))))) | G31: =IF(C31=0,"⬜",IF(C31/B31<0.8,"🟢",IF(C31/B31<=1,"🟡","🔴")))
A32: Total Crédits | B32: =SUM(B29:B31) | C32: =SUM(C29:C31) | D32: =SUM(D29:D31) | E32: =IF(B32=0,0,C32/B32) | F32: =IF(B32=0,"",REPT("▓",MIN(20,INT(C32/B32*20)))&REPT("░",MAX(0,20-MIN(20,INT(C32/B32*20)))))
A34: 🏦 ÉPARGNE
A35: Livret A | B35: 0 | C35: 0 | D35: =B35-C35 | E35: =IF(B35=0,"—",C35/B35) | F35: =IF(B35=0,"",REPT("▓",MIN(20,INT(C35/B35*20)))&REPT("░",MAX(0,20-MIN(20,INT(C35/B35*20))))) | G35: =IF(C35=0,"⬜",IF(C35/B35<0.8,"🟢",IF(C35/B35<=1,"🟡","🔴")))
A36: PEL / CEL | B36: 0 | C36: 0 | D36: =B36-C36 | E36: =IF(B36=0,"—",C36/B36) | F36: =IF(B36=0,"",REPT("▓",MIN(20,INT(C36/B36*20)))&REPT("░",MAX(0,20-MIN(20,INT(C36/B36*20))))) | G36: =IF(C36=0,"⬜",IF(C36/B36<0.8,"🟢",IF(C36/B36<=1,"🟡","🔴")))
A37: Assurance-vie | B37: 0 | C37: 0 | D37: =B37-C37 | E37: =IF(B37=0,"—",C37/B37) | F37: =IF(B37=0,"",REPT("▓",MIN(20,INT(C37/B37*20)))&REPT("░",MAX(0,20-MIN(20,INT(C37/B37*20))))) | G37: =IF(C37=0,"⬜",IF(C37/B37<0.8,"🟢",IF(C37/B37<=1,"🟡","🔴")))
A38: Investissements | B38: 0 | C38: 0 | D38: =B38-C38 | E38: =IF(B38=0,"—",C38/B38) | F38: =IF(B38=0,"",REPT("▓",MIN(20,INT(C38/B38*20)))&REPT("░",MAX(0,20-MIN(20,INT(C38/B38*20))))) | G38: =IF(C38=0,"⬜",IF(C38/B38<0.8,"🟢",IF(C38/B38<=1,"🟡","🔴")))
A39: Total Épargne | B39: =SUM(B35:B38) | C39: =SUM(C35:C38) | D39: =SUM(D35:D38) | E39: =IF(B39=0,0,C39/B39) | F39: =IF(B39=0,"",REPT("▓",MIN(20,INT(C39/B39*20)))&REPT("░",MAX(0,20-MIN(20,INT(C39/B39*20)))))
A42: ✦ BILAN DU MOIS
A43: 💰 Total Revenus | F43: =C8
A44: 💸 Total Dépenses | F44: =C15+C26+C32
A45: 📊 Solde du mois | F45: =C8-(C15+C26+C32)
A46: 🎯 Taux d'épargne | F46: =IF(C8=0,0,(C8-(C15+C26+C32))/C8)
A47: 🏦 Épargne réelle | F47: =C39

Sheet Juin
A1: ✦ JUIN ✦
A2: Catégorie | B2: Budget prévu | C2: Réel dépensé | D2: Écart | E2: % utilisé | F2: Progression
A3: 💰 REVENUS
A4: Salaire net | B4: 0 | C4: 0 | D4: =B4-C4 | E4: =IF(B4=0,"—",C4/B4) | F4: =IF(B4=0,"",REPT("▓",MIN(20,INT(C4/B4*20)))&REPT("░",MAX(0,20-MIN(20,INT(C4/B4*20))))) | G4: =IF(C4=0,"⬜",IF(C4/B4<0.8,"🟢",IF(C4/B4<=1,"🟡","🔴")))
A5: Freelance / Side | B5: 0 | C5: 0 | D5: =B5-C5 | E5: =IF(B5=0,"—",C5/B5) | F5: =IF(B5=0,"",REPT("▓",MIN(20,INT(C5/B5*20)))&REPT("░",MAX(0,20-MIN(20,INT(C5/B5*20))))) | G5: =IF(C5=0,"⬜",IF(C5/B5<0.8,"🟢",IF(C5/B5<=1,"🟡","🔴")))
A6: Aides / APL | B6: 0 | C6: 0 | D6: =B6-C6 | E6: =IF(B6=0,"—",C6/B6) | F6: =IF(B6=0,"",REPT("▓",MIN(20,INT(C6/B6*20)))&REPT("░",MAX(0,20-MIN(20,INT(C6/B6*20))))) | G6: =IF(C6=0,"⬜",IF(C6/B6<0.8,"🟢",IF(C6/B6<=1,"🟡","🔴")))
A7: Autres revenus | B7: 0 | C7: 0 | D7: =B7-C7 | E7: =IF(B7=0,"—",C7/B7) | F7: =IF(B7=0,"",REPT("▓",MIN(20,INT(C7/B7*20)))&REPT("░",MAX(0,20-MIN(20,INT(C7/B7*20))))) | G7: =IF(C7=0,"⬜",IF(C7/B7<0.8,"🟢",IF(C7/B7<=1,"🟡","🔴")))
A8: Total Revenus | B8: =SUM(B4:B7) | C8: =SUM(C4:C7) | D8: =SUM(D4:D7) | E8: =IF(B8=0,0,C8/B8) | F8: =IF(B8=0,"",REPT("▓",MIN(20,INT(C8/B8*20)))&REPT("░",MAX(0,20-MIN(20,INT(C8/B8*20)))))
A10: 🏠 DÉPENSES FIXES
A11: Loyer / Crédit immo | B11: 0 | C11: 0 | D11: =B11-C11 | E11: =IF(B11=0,"—",C11/B11) | F11: =IF(B11=0,"",REPT("▓",MIN(20,INT(C11/B11*20)))&REPT("░",MAX(0,20-MIN(20,INT(C11/B11*20))))) | G11: =IF(C11=0,"⬜",IF(C11/B11<0.8,"🟢",IF(C11/B11<=1,"🟡","🔴")))
A12: Assurances | B12: 0 | C12: 0 | D12: =B12-C12 | E12: =IF(B12=0,"—",C12/B12) | F12: =IF(B12=0,"",REPT("▓",MIN(20,INT(C12/B12*20)))&REPT("░",MAX(0,20-MIN(20,INT(C12/B12*20))))) | G12: =IF(C12=0,"⬜",IF(C12/B12<0.8,"🟢",IF(C12/B12<=1,"🟡","🔴")))
A13: Abonnements | B13: 0 | C13: 0 | D13: =B13-C13 | E13: =IF(B13=0,"—",C13/B13) | F13: =IF(B13=0,"",REPT("▓",MIN(20,INT(C13/B13*20)))&REPT("░",MAX(0,20-MIN(20,INT(C13/B13*20))))) | G13: =IF(C13=0,"⬜",IF(C13/B13<0.8,"🟢",IF(C13/B13<=1,"🟡","🔴")))
A14: Téléphone / Internet | B14: 0 | C14: 0 | D14: =B14-C14 | E14: =IF(B14=0,"—",C14/B14) | F14: =IF(B14=0,"",REPT("▓",MIN(20,INT(C14/B14*20)))&REPT("░",MAX(0,20-MIN(20,INT(C14/B14*20))))) | G14: =IF(C14=0,"⬜",IF(C14/B14<0.8,"🟢",IF(C14/B14<=1,"🟡","🔴")))
A15: Total Fixes | B15: =SUM(B11:B14) | C15: =SUM(C11:C14) | D15: =SUM(D11:D14) | E15: =IF(B15=0,0,C15/B15) | F15: =IF(B15=0,"",REPT("▓",MIN(20,INT(C15/B15*20)))&REPT("░",MAX(0,20-MIN(20,INT(C15/B15*20)))))
A17: 🛒 DÉPENSES VARIABLES
A18: Alimentation | B18: 0 | C18: 0 | D18: =B18-C18 | E18: =IF(B18=0,"—",C18/B18) | F18: =IF(B18=0,"",REPT("▓",MIN(20,INT(C18/B18*20)))&REPT("░",MAX(0,20-MIN(20,INT(C18/B18*20))))) | G18: =IF(C18=0,"⬜",IF(C18/B18<0.8,"🟢",IF(C18/B18<=1,"🟡","🔴")))
A19: Transport | B19: 0 | C19: 0 | D19: =B19-C19 | E19: =IF(B19=0,"—",C19/B19) | F19: =IF(B19=0,"",REPT("▓",MIN(20,INT(C19/B19*20)))&REPT("░",MAX(0,20-MIN(20,INT(C19/B19*20))))) | G19: =IF(C19=0,"⬜",IF(C19/B19<0.8,"🟢",IF(C19/B19<=1,"🟡","🔴")))
A20: Santé | B20: 0 | C20: 0 | D20: =B20-C20 | E20: =IF(B20=0,"—",C20/B20) | F20: =IF(B20=0,"",REPT("▓",MIN(20,INT(C20/B20*20)))&REPT("░",MAX(0,20-MIN(20,INT(C20/B20*20))))) | G20: =IF(C20=0,"⬜",IF(C20/B20<0.8,"🟢",IF(C20/B20<=1,"🟡","🔴")))
A21: Loisirs | B21: 0 | C21: 0 | D21: =B21-C21 | E21: =IF(B21=0,"—",C21/B21) | F21: =IF(B21=0,"",REPT("▓",MIN(20,INT(C21/B21*20)))&REPT("░",MAX(0,20-MIN(20,INT(C21/B21*20))))) | G21: =IF(C21=0,"⬜",IF(C21/B21<0.8,"🟢",IF(C21/B21<=1,"🟡","🔴")))
A22: Shopping | B22: 0 | C22: 0 | D22: =B22-C22 | E22: =IF(B22=0,"—",C22/B22) | F22: =IF(B22=0,"",REPT("▓",MIN(20,INT(C22/B22*20)))&REPT("░",MAX(0,20-MIN(20,INT(C22/B22*20))))) | G22: =IF(C22=0,"⬜",IF(C22/B22<0.8,"🟢",IF(C22/B22<=1,"🟡","🔴")))
A23: Restaurant | B23: 0 | C23: 0 | D23: =B23-C23 | E23: =IF(B23=0,"—",C23/B23) | F23: =IF(B23=0,"",REPT("▓",MIN(20,INT(C23/B23*20)))&REPT("░",MAX(0,20-MIN(20,INT(C23/B23*20))))) | G23: =IF(C23=0,"⬜",IF(C23/B23<0.8,"🟢",IF(C23/B23<=1,"🟡","🔴")))
A24: Beauté | B24: 0 | C24: 0 | D24: =B24-C24 | E24: =IF(B24=0,"—",C24/B24) | F24: =IF(B24=0,"",REPT("▓",MIN(20,INT(C24/B24*20)))&REPT("░",MAX(0,20-MIN(20,INT(C24/B24*20))))) | G24: =IF(C24=0,"⬜",IF(C24/B24<0.8,"🟢",IF(C24/B24<=1,"🟡","🔴")))
A25: Autre | B25: 0 | C25: 0 | D25: =B25-C25 | E25: =IF(B25=0,"—",C25/B25) | F25: =IF(B25=0,"",REPT("▓",MIN(20,INT(C25/B25*20)))&REPT("░",MAX(0,20-MIN(20,INT(C25/B25*20))))) | G25: =IF(C25=0,"⬜",IF(C25/B25<0.8,"🟢",IF(C25/B25<=1,"🟡","🔴")))
A26: Total Variables | B26: =SUM(B18:B25) | C26: =SUM(C18:C25) | D26: =SUM(D18:D25) | E26: =IF(B26=0,0,C26/B26) | F26: =IF(B26=0,"",REPT("▓",MIN(20,INT(C26/B26*20)))&REPT("░",MAX(0,20-MIN(20,INT(C26/B26*20)))))
A28: 💳 CRÉDITS
A29: Crédit auto | B29: 0 | C29: 0 | D29: =B29-C29 | E29: =IF(B29=0,"—",C29/B29) | F29: =IF(B29=0,"",REPT("▓",MIN(20,INT(C29/B29*20)))&REPT("░",MAX(0,20-MIN(20,INT(C29/B29*20))))) | G29: =IF(C29=0,"⬜",IF(C29/B29<0.8,"🟢",IF(C29/B29<=1,"🟡","🔴")))
A30: Crédit conso | B30: 0 | C30: 0 | D30: =B30-C30 | E30: =IF(B30=0,"—",C30/B30) | F30: =IF(B30=0,"",REPT("▓",MIN(20,INT(C30/B30*20)))&REPT("░",MAX(0,20-MIN(20,INT(C30/B30*20))))) | G30: =IF(C30=0,"⬜",IF(C30/B30<0.8,"🟢",IF(C30/B30<=1,"🟡","🔴")))
A31: Autre crédit | B31: 0 | C31: 0 | D31: =B31-C31 | E31: =IF(B31=0,"—",C31/B31) | F31: =IF(B31=0,"",REPT("▓",MIN(20,INT(C31/B31*20)))&REPT("░",MAX(0,20-MIN(20,INT(C31/B31*20))))) | G31: =IF(C31=0,"⬜",IF(C31/B31<0.8,"🟢",IF(C31/B31<=1,"🟡","🔴")))
A32: Total Crédits | B32: =SUM(B29:B31) | C32: =SUM(C29:C31) | D32: =SUM(D29:D31) | E32: =IF(B32=0,0,C32/B32) | F32: =IF(B32=0,"",REPT("▓",MIN(20,INT(C32/B32*20)))&REPT("░",MAX(0,20-MIN(20,INT(C32/B32*20)))))
A34: 🏦 ÉPARGNE
A35: Livret A | B35: 0 | C35: 0 | D35: =B35-C35 | E35: =IF(B35=0,"—",C35/B35) | F35: =IF(B35=0,"",REPT("▓",MIN(20,INT(C35/B35*20)))&REPT("░",MAX(0,20-MIN(20,INT(C35/B35*20))))) | G35: =IF(C35=0,"⬜",IF(C35/B35<0.8,"🟢",IF(C35/B35<=1,"🟡","🔴")))
A36: PEL / CEL | B36: 0 | C36: 0 | D36: =B36-C36 | E36: =IF(B36=0,"—",C36/B36) | F36: =IF(B36=0,"",REPT("▓",MIN(20,INT(C36/B36*20)))&REPT("░",MAX(0,20-MIN(20,INT(C36/B36*20))))) | G36: =IF(C36=0,"⬜",IF(C36/B36<0.8,"🟢",IF(C36/B36<=1,"🟡","🔴")))
A37: Assurance-vie | B37: 0 | C37: 0 | D37: =B37-C37 | E37: =IF(B37=0,"—",C37/B37) | F37: =IF(B37=0,"",REPT("▓",MIN(20,INT(C37/B37*20)))&REPT("░",MAX(0,20-MIN(20,INT(C37/B37*20))))) | G37: =IF(C37=0,"⬜",IF(C37/B37<0.8,"🟢",IF(C37/B37<=1,"🟡","🔴")))
A38: Investissements | B38: 0 | C38: 0 | D38: =B38-C38 | E38: =IF(B38=0,"—",C38/B38) | F38: =IF(B38=0,"",REPT("▓",MIN(20,INT(C38/B38*20)))&REPT("░",MAX(0,20-MIN(20,INT(C38/B38*20))))) | G38: =IF(C38=0,"⬜",IF(C38/B38<0.8,"🟢",IF(C38/B38<=1,"🟡","🔴")))
A39: Total Épargne | B39: =SUM(B35:B38) | C39: =SUM(C35:C38) | D39: =SUM(D35:D38) | E39: =IF(B39=0,0,C39/B39) | F39: =IF(B39=0,"",REPT("▓",MIN(20,INT(C39/B39*20)))&REPT("░",MAX(0,20-MIN(20,INT(C39/B39*20)))))
A42: ✦ BILAN DU MOIS
A43: 💰 Total Revenus | F43: =C8
A44: 💸 Total Dépenses | F44: =C15+C26+C32
A45: 📊 Solde du mois | F45: =C8-(C15+C26+C32)
A46: 🎯 Taux d'épargne | F46: =IF(C8=0,0,(C8-(C15+C26+C32))/C8)
A47: 🏦 Épargne réelle | F47: =C39

Sheet Juillet
A1: ✦ JUILLET ✦
A2: Catégorie | B2: Budget prévu | C2: Réel dépensé | D2: Écart | E2: % utilisé | F2: Progression
A3: 💰 REVENUS
A4: Salaire net | B4: 0 | C4: 0 | D4: =B4-C4 | E4: =IF(B4=0,"—",C4/B4) | F4: =IF(B4=0,"",REPT("▓",MIN(20,INT(C4/B4*20)))&REPT("░",MAX(0,20-MIN(20,INT(C4/B4*20))))) | G4: =IF(C4=0,"⬜",IF(C4/B4<0.8,"🟢",IF(C4/B4<=1,"🟡","🔴")))
A5: Freelance / Side | B5: 0 | C5: 0 | D5: =B5-C5 | E5: =IF(B5=0,"—",C5/B5) | F5: =IF(B5=0,"",REPT("▓",MIN(20,INT(C5/B5*20)))&REPT("░",MAX(0,20-MIN(20,INT(C5/B5*20))))) | G5: =IF(C5=0,"⬜",IF(C5/B5<0.8,"🟢",IF(C5/B5<=1,"🟡","🔴")))
A6: Aides / APL | B6: 0 | C6: 0 | D6: =B6-C6 | E6: =IF(B6=0,"—",C6/B6) | F6: =IF(B6=0,"",REPT("▓",MIN(20,INT(C6/B6*20)))&REPT("░",MAX(0,20-MIN(20,INT(C6/B6*20))))) | G6: =IF(C6=0,"⬜",IF(C6/B6<0.8,"🟢",IF(C6/B6<=1,"🟡","🔴")))
A7: Autres revenus | B7: 0 | C7: 0 | D7: =B7-C7 | E7: =IF(B7=0,"—",C7/B7) | F7: =IF(B7=0,"",REPT("▓",MIN(20,INT(C7/B7*20)))&REPT("░",MAX(0,20-MIN(20,INT(C7/B7*20))))) | G7: =IF(C7=0,"⬜",IF(C7/B7<0.8,"🟢",IF(C7/B7<=1,"🟡","🔴")))
A8: Total Revenus | B8: =SUM(B4:B7) | C8: =SUM(C4:C7) | D8: =SUM(D4:D7) | E8: =IF(B8=0,0,C8/B8) | F8: =IF(B8=0,"",REPT("▓",MIN(20,INT(C8/B8*20)))&REPT("░",MAX(0,20-MIN(20,INT(C8/B8*20)))))
A10: 🏠 DÉPENSES FIXES
A11: Loyer / Crédit immo | B11: 0 | C11: 0 | D11: =B11-C11 | E11: =IF(B11=0,"—",C11/B11) | F11: =IF(B11=0,"",REPT("▓",MIN(20,INT(C11/B11*20)))&REPT("░",MAX(0,20-MIN(20,INT(C11/B11*20))))) | G11: =IF(C11=0,"⬜",IF(C11/B11<0.8,"🟢",IF(C11/B11<=1,"🟡","🔴")))
A12: Assurances | B12: 0 | C12: 0 | D12: =B12-C12 | E12: =IF(B12=0,"—",C12/B12) | F12: =IF(B12=0,"",REPT("▓",MIN(20,INT(C12/B12*20)))&REPT("░",MAX(0,20-MIN(20,INT(C12/B12*20))))) | G12: =IF(C12=0,"⬜",IF(C12/B12<0.8,"🟢",IF(C12/B12<=1,"🟡","🔴")))
A13: Abonnements | B13: 0 | C13: 0 | D13: =B13-C13 | E13: =IF(B13=0,"—",C13/B13) | F13: =IF(B13=0,"",REPT("▓",MIN(20,INT(C13/B13*20)))&REPT("░",MAX(0,20-MIN(20,INT(C13/B13*20))))) | G13: =IF(C13=0,"⬜",IF(C13/B13<0.8,"🟢",IF(C13/B13<=1,"🟡","🔴")))
A14: Téléphone / Internet | B14: 0 | C14: 0 | D14: =B14-C14 | E14: =IF(B14=0,"—",C14/B14) | F14: =IF(B14=0,"",REPT("▓",MIN(20,INT(C14/B14*20)))&REPT("░",MAX(0,20-MIN(20,INT(C14/B14*20))))) | G14: =IF(C14=0,"⬜",IF(C14/B14<0.8,"🟢",IF(C14/B14<=1,"🟡","🔴")))
A15: Total Fixes | B15: =SUM(B11:B14) | C15: =SUM(C11:C14) | D15: =SUM(D11:D14) | E15: =IF(B15=0,0,C15/B15) | F15: =IF(B15=0,"",REPT("▓",MIN(20,INT(C15/B15*20)))&REPT("░",MAX(0,20-MIN(20,INT(C15/B15*20)))))
A17: 🛒 DÉPENSES VARIABLES
A18: Alimentation | B18: 0 | C18: 0 | D18: =B18-C18 | E18: =IF(B18=0,"—",C18/B18) | F18: =IF(B18=0,"",REPT("▓",MIN(20,INT(C18/B18*20)))&REPT("░",MAX(0,20-MIN(20,INT(C18/B18*20))))) | G18: =IF(C18=0,"⬜",IF(C18/B18<0.8,"🟢",IF(C18/B18<=1,"🟡","🔴")))
A19: Transport | B19: 0 | C19: 0 | D19: =B19-C19 | E19: =IF(B19=0,"—",C19/B19) | F19: =IF(B19=0,"",REPT("▓",MIN(20,INT(C19/B19*20)))&REPT("░",MAX(0,20-MIN(20,INT(C19/B19*20))))) | G19: =IF(C19=0,"⬜",IF(C19/B19<0.8,"🟢",IF(C19/B19<=1,"🟡","🔴")))
A20: Santé | B20: 0 | C20: 0 | D20: =B20-C20 | E20: =IF(B20=0,"—",C20/B20) | F20: =IF(B20=0,"",REPT("▓",MIN(20,INT(C20/B20*20)))&REPT("░",MAX(0,20-MIN(20,INT(C20/B20*20))))) | G20: =IF(C20=0,"⬜",IF(C20/B20<0.8,"🟢",IF(C20/B20<=1,"🟡","🔴")))
A21: Loisirs | B21: 0 | C21: 0 | D21: =B21-C21 | E21: =IF(B21=0,"—",C21/B21) | F21: =IF(B21=0,"",REPT("▓",MIN(20,INT(C21/B21*20)))&REPT("░",MAX(0,20-MIN(20,INT(C21/B21*20))))) | G21: =IF(C21=0,"⬜",IF(C21/B21<0.8,"🟢",IF(C21/B21<=1,"🟡","🔴")))
A22: Shopping | B22: 0 | C22: 0 | D22: =B22-C22 | E22: =IF(B22=0,"—",C22/B22) | F22: =IF(B22=0,"",REPT("▓",MIN(20,INT(C22/B22*20)))&REPT("░",MAX(0,20-MIN(20,INT(C22/B22*20))))) | G22: =IF(C22=0,"⬜",IF(C22/B22<0.8,"🟢",IF(C22/B22<=1,"🟡","🔴")))
A23: Restaurant | B23: 0 | C23: 0 | D23: =B23-C23 | E23: =IF(B23=0,"—",C23/B23) | F23: =IF(B23=0,"",REPT("▓",MIN(20,INT(C23/B23*20)))&REPT("░",MAX(0,20-MIN(20,INT(C23/B23*20))))) | G23: =IF(C23=0,"⬜",IF(C23/B23<0.8,"🟢",IF(C23/B23<=1,"🟡","🔴")))
A24: Beauté | B24: 0 | C24: 0 | D24: =B24-C24 | E24: =IF(B24=0,"—",C24/B24) | F24: =IF(B24=0,"",REPT("▓",MIN(20,INT(C24/B24*20)))&REPT("░",MAX(0,20-MIN(20,INT(C24/B24*20))))) | G24: =IF(C24=0,"⬜",IF(C24/B24<0.8,"🟢",IF(C24/B24<=1,"🟡","🔴")))
A25: Autre | B25: 0 | C25: 0 | D25: =B25-C25 | E25: =IF(B25=0,"—",C25/B25) | F25: =IF(B25=0,"",REPT("▓",MIN(20,INT(C25/B25*20)))&REPT("░",MAX(0,20-MIN(20,INT(C25/B25*20))))) | G25: =IF(C25=0,"⬜",IF(C25/B25<0.8,"🟢",IF(C25/B25<=1,"🟡","🔴")))
A26: Total Variables | B26: =SUM(B18:B25) | C26: =SUM(C18:C25) | D26: =SUM(D18:D25) | E26: =IF(B26=0,0,C26/B26) | F26: =IF(B26=0,"",REPT("▓",MIN(20,INT(C26/B26*20)))&REPT("░",MAX(0,20-MIN(20,INT(C26/B26*20)))))
A28: 💳 CRÉDITS
A29: Crédit auto | B29: 0 | C29: 0 | D29: =B29-C29 | E29: =IF(B29=0,"—",C29/B29) | F29: =IF(B29=0,"",REPT("▓",MIN(20,INT(C29/B29*20)))&REPT("░",MAX(0,20-MIN(20,INT(C29/B29*20))))) | G29: =IF(C29=0,"⬜",IF(C29/B29<0.8,"🟢",IF(C29/B29<=1,"🟡","🔴")))
A30: Crédit conso | B30: 0 | C30: 0 | D30: =B30-C30 | E30: =IF(B30=0,"—",C30/B30) | F30: =IF(B30=0,"",REPT("▓",MIN(20,INT(C30/B30*20)))&REPT("░",MAX(0,20-MIN(20,INT(C30/B30*20))))) | G30: =IF(C30=0,"⬜",IF(C30/B30<0.8,"🟢",IF(C30/B30<=1,"🟡","🔴")))
A31: Autre crédit | B31: 0 | C31: 0 | D31: =B31-C31 | E31: =IF(B31=0,"—",C31/B31) | F31: =IF(B31=0,"",REPT("▓",MIN(20,INT(C31/B31*20)))&REPT("░",MAX(0,20-MIN(20,INT(C31/B31*20))))) | G31: =IF(C31=0,"⬜",IF(C31/B31<0.8,"🟢",IF(C31/B31<=1,"🟡","🔴")))
A32: Total Crédits | B32: =SUM(B29:B31) | C32: =SUM(C29:C31) | D32: =SUM(D29:D31) | E32: =IF(B32=0,0,C32/B32) | F32: =IF(B32=0,"",REPT("▓",MIN(20,INT(C32/B32*20)))&REPT("░",MAX(0,20-MIN(20,INT(C32/B32*20)))))
A34: 🏦 ÉPARGNE
A35: Livret A | B35: 0 | C35: 0 | D35: =B35-C35 | E35: =IF(B35=0,"—",C35/B35) | F35: =IF(B35=0,"",REPT("▓",MIN(20,INT(C35/B35*20)))&REPT("░",MAX(0,20-MIN(20,INT(C35/B35*20))))) | G35: =IF(C35=0,"⬜",IF(C35/B35<0.8,"🟢",IF(C35/B35<=1,"🟡","🔴")))
A36: PEL / CEL | B36: 0 | C36: 0 | D36: =B36-C36 | E36: =IF(B36=0,"—",C36/B36) | F36: =IF(B36=0,"",REPT("▓",MIN(20,INT(C36/B36*20)))&REPT("░",MAX(0,20-MIN(20,INT(C36/B36*20))))) | G36: =IF(C36=0,"⬜",IF(C36/B36<0.8,"🟢",IF(C36/B36<=1,"🟡","🔴")))
A37: Assurance-vie | B37: 0 | C37: 0 | D37: =B37-C37 | E37: =IF(B37=0,"—",C37/B37) | F37: =IF(B37=0,"",REPT("▓",MIN(20,INT(C37/B37*20)))&REPT("░",MAX(0,20-MIN(20,INT(C37/B37*20))))) | G37: =IF(C37=0,"⬜",IF(C37/B37<0.8,"🟢",IF(C37/B37<=1,"🟡","🔴")))
A38: Investissements | B38: 0 | C38: 0 | D38: =B38-C38 | E38: =IF(B38=0,"—",C38/B38) | F38: =IF(B38=0,"",REPT("▓",MIN(20,INT(C38/B38*20)))&REPT("░",MAX(0,20-MIN(20,INT(C38/B38*20))))) | G38: =IF(C38=0,"⬜",IF(C38/B38<0.8,"🟢",IF(C38/B38<=1,"🟡","🔴")))
A39: Total Épargne | B39: =SUM(B35:B38) | C39: =SUM(C35:C38) | D39: =SUM(D35:D38) | E39: =IF(B39=0,0,C39/B39) | F39: =IF(B39=0,"",REPT("▓",MIN(20,INT(C39/B39*20)))&REPT("░",MAX(0,20-MIN(20,INT(C39/B39*20)))))
A42: ✦ BILAN DU MOIS
A43: 💰 Total Revenus | F43: =C8
A44: 💸 Total Dépenses | F44: =C15+C26+C32
A45: 📊 Solde du mois | F45: =C8-(C15+C26+C32)
A46: 🎯 Taux d'épargne | F46: =IF(C8=0,0,(C8-(C15+C26+C32))/C8)
A47: 🏦 Épargne réelle | F47: =C39

Sheet Aout
A1: ✦ AOÛT ✦
A2: Catégorie | B2: Budget prévu | C2: Réel dépensé | D2: Écart | E2: % utilisé | F2: Progression
A3: 💰 REVENUS
A4: Salaire net | B4: 0 | C4: 0 | D4: =B4-C4 | E4: =IF(B4=0,"—",C4/B4) | F4: =IF(B4=0,"",REPT("▓",MIN(20,INT(C4/B4*20)))&REPT("░",MAX(0,20-MIN(20,INT(C4/B4*20))))) | G4: =IF(C4=0,"⬜",IF(C4/B4<0.8,"🟢",IF(C4/B4<=1,"🟡","🔴")))
A5: Freelance / Side | B5: 0 | C5: 0 | D5: =B5-C5 | E5: =IF(B5=0,"—",C5/B5) | F5: =IF(B5=0,"",REPT("▓",MIN(20,INT(C5/B5*20)))&REPT("░",MAX(0,20-MIN(20,INT(C5/B5*20))))) | G5: =IF(C5=0,"⬜",IF(C5/B5<0.8,"🟢",IF(C5/B5<=1,"🟡","🔴")))
A6: Aides / APL | B6: 0 | C6: 0 | D6: =B6-C6 | E6: =IF(B6=0,"—",C6/B6) | F6: =IF(B6=0,"",REPT("▓",MIN(20,INT(C6/B6*20)))&REPT("░",MAX(0,20-MIN(20,INT(C6/B6*20))))) | G6: =IF(C6=0,"⬜",IF(C6/B6<0.8,"🟢",IF(C6/B6<=1,"🟡","🔴")))
A7: Autres revenus | B7: 0 | C7: 0 | D7: =B7-C7 | E7: =IF(B7=0,"—",C7/B7) | F7: =IF(B7=0,"",REPT("▓",MIN(20,INT(C7/B7*20)))&REPT("░",MAX(0,20-MIN(20,INT(C7/B7*20))))) | G7: =IF(C7=0,"⬜",IF(C7/B7<0.8,"🟢",IF(C7/B7<=1,"🟡","🔴")))
A8: Total Revenus | B8: =SUM(B4:B7) | C8: =SUM(C4:C7) | D8: =SUM(D4:D7) | E8: =IF(B8=0,0,C8/B8) | F8: =IF(B8=0,"",REPT("▓",MIN(20,INT(C8/B8*20)))&REPT("░",MAX(0,20-MIN(20,INT(C8/B8*20)))))
A10: 🏠 DÉPENSES FIXES
A11: Loyer / Crédit immo | B11: 0 | C11: 0 | D11: =B11-C11 | E11: =IF(B11=0,"—",C11/B11) | F11: =IF(B11=0,"",REPT("▓",MIN(20,INT(C11/B11*20)))&REPT("░",MAX(0,20-MIN(20,INT(C11/B11*20))))) | G11: =IF(C11=0,"⬜",IF(C11/B11<0.8,"🟢",IF(C11/B11<=1,"🟡","🔴")))
A12: Assurances | B12: 0 | C12: 0 | D12: =B12-C12 | E12: =IF(B12=0,"—",C12/B12) | F12: =IF(B12=0,"",REPT("▓",MIN(20,INT(C12/B12*20)))&REPT("░",MAX(0,20-MIN(20,INT(C12/B12*20))))) | G12: =IF(C12=0,"⬜",IF(C12/B12<0.8,"🟢",IF(C12/B12<=1,"🟡","🔴")))
A13: Abonnements | B13: 0 | C13: 0 | D13: =B13-C13 | E13: =IF(B13=0,"—",C13/B13) | F13: =IF(B13=0,"",REPT("▓",MIN(20,INT(C13/B13*20)))&REPT("░",MAX(0,20-MIN(20,INT(C13/B13*20))))) | G13: =IF(C13=0,"⬜",IF(C13/B13<0.8,"🟢",IF(C13/B13<=1,"🟡","🔴")))
A14: Téléphone / Internet | B14: 0 | C14: 0 | D14: =B14-C14 | E14: =IF(B14=0,"—",C14/B14) | F14: =IF(B14=0,"",REPT("▓",MIN(20,INT(C14/B14*20)))&REPT("░",MAX(0,20-MIN(20,INT(C14/B14*20))))) | G14: =IF(C14=0,"⬜",IF(C14/B14<0.8,"🟢",IF(C14/B14<=1,"🟡","🔴")))
A15: Total Fixes | B15: =SUM(B11:B14) | C15: =SUM(C11:C14) | D15: =SUM(D11:D14) | E15: =IF(B15=0,0,C15/B15) | F15: =IF(B15=0,"",REPT("▓",MIN(20,INT(C15/B15*20)))&REPT("░",MAX(0,20-MIN(20,INT(C15/B15*20)))))
A17: 🛒 DÉPENSES VARIABLES
A18: Alimentation | B18: 0 | C18: 0 | D18: =B18-C18 | E18: =IF(B18=0,"—",C18/B18) | F18: =IF(B18=0,"",REPT("▓",MIN(20,INT(C18/B18*20)))&REPT("░",MAX(0,20-MIN(20,INT(C18/B18*20))))) | G18: =IF(C18=0,"⬜",IF(C18/B18<0.8,"🟢",IF(C18/B18<=1,"🟡","🔴")))
A19: Transport | B19: 0 | C19: 0 | D19: =B19-C19 | E19: =IF(B19=0,"—",C19/B19) | F19: =IF(B19=0,"",REPT("▓",MIN(20,INT(C19/B19*20)))&REPT("░",MAX(0,20-MIN(20,INT(C19/B19*20))))) | G19: =IF(C19=0,"⬜",IF(C19/B19<0.8,"🟢",IF(C19/B19<=1,"🟡","🔴")))
A20: Santé | B20: 0 | C20: 0 | D20: =B20-C20 | E20: =IF(B20=0,"—",C20/B20) | F20: =IF(B20=0,"",REPT("▓",MIN(20,INT(C20/B20*20)))&REPT("░",MAX(0,20-MIN(20,INT(C20/B20*20))))) | G20: =IF(C20=0,"⬜",IF(C20/B20<0.8,"🟢",IF(C20/B20<=1,"🟡","🔴")))
A21: Loisirs | B21: 0 | C21: 0 | D21: =B21-C21 | E21: =IF(B21=0,"—",C21/B21) | F21: =IF(B21=0,"",REPT("▓",MIN(20,INT(C21/B21*20)))&REPT("░",MAX(0,20-MIN(20,INT(C21/B21*20))))) | G21: =IF(C21=0,"⬜",IF(C21/B21<0.8,"🟢",IF(C21/B21<=1,"🟡","🔴")))
A22: Shopping | B22: 0 | C22: 0 | D22: =B22-C22 | E22: =IF(B22=0,"—",C22/B22) | F22: =IF(B22=0,"",REPT("▓",MIN(20,INT(C22/B22*20)))&REPT("░",MAX(0,20-MIN(20,INT(C22/B22*20))))) | G22: =IF(C22=0,"⬜",IF(C22/B22<0.8,"🟢",IF(C22/B22<=1,"🟡","🔴")))
A23: Restaurant | B23: 0 | C23: 0 | D23: =B23-C23 | E23: =IF(B23=0,"—",C23/B23) | F23: =IF(B23=0,"",REPT("▓",MIN(20,INT(C23/B23*20)))&REPT("░",MAX(0,20-MIN(20,INT(C23/B23*20))))) | G23: =IF(C23=0,"⬜",IF(C23/B23<0.8,"🟢",IF(C23/B23<=1,"🟡","🔴")))
A24: Beauté | B24: 0 | C24: 0 | D24: =B24-C24 | E24: =IF(B24=0,"—",C24/B24) | F24: =IF(B24=0,"",REPT("▓",MIN(20,INT(C24/B24*20)))&REPT("░",MAX(0,20-MIN(20,INT(C24/B24*20))))) | G24: =IF(C24=0,"⬜",IF(C24/B24<0.8,"🟢",IF(C24/B24<=1,"🟡","🔴")))
A25: Autre | B25: 0 | C25: 0 | D25: =B25-C25 | E25: =IF(B25=0,"—",C25/B25) | F25: =IF(B25=0,"",REPT("▓",MIN(20,INT(C25/B25*20)))&REPT("░",MAX(0,20-MIN(20,INT(C25/B25*20))))) | G25: =IF(C25=0,"⬜",IF(C25/B25<0.8,"🟢",IF(C25/B25<=1,"🟡","🔴")))
A26: Total Variables | B26: =SUM(B18:B25) | C26: =SUM(C18:C25) | D26: =SUM(D18:D25) | E26: =IF(B26=0,0,C26/B26) | F26: =IF(B26=0,"",REPT("▓",MIN(20,INT(C26/B26*20)))&REPT("░",MAX(0,20-MIN(20,INT(C26/B26*20)))))
A28: 💳 CRÉDITS
A29: Crédit auto | B29: 0 | C29: 0 | D29: =B29-C29 | E29: =IF(B29=0,"—",C29/B29) | F29: =IF(B29=0,"",REPT("▓",MIN(20,INT(C29/B29*20)))&REPT("░",MAX(0,20-MIN(20,INT(C29/B29*20))))) | G29: =IF(C29=0,"⬜",IF(C29/B29<0.8,"🟢",IF(C29/B29<=1,"🟡","🔴")))
A30: Crédit conso | B30: 0 | C30: 0 | D30: =B30-C30 | E30: =IF(B30=0,"—",C30/B30) | F30: =IF(B30=0,"",REPT("▓",MIN(20,INT(C30/B30*20)))&REPT("░",MAX(0,20-MIN(20,INT(C30/B30*20))))) | G30: =IF(C30=0,"⬜",IF(C30/B30<0.8,"🟢",IF(C30/B30<=1,"🟡","🔴")))
A31: Autre crédit | B31: 0 | C31: 0 | D31: =B31-C31 | E31: =IF(B31=0,"—",C31/B31) | F31: =IF(B31=0,"",REPT("▓",MIN(20,INT(C31/B31*20)))&REPT("░",MAX(0,20-MIN(20,INT(C31/B31*20))))) | G31: =IF(C31=0,"⬜",IF(C31/B31<0.8,"🟢",IF(C31/B31<=1,"🟡","🔴")))
A32: Total Crédits | B32: =SUM(B29:B31) | C32: =SUM(C29:C31) | D32: =SUM(D29:D31) | E32: =IF(B32=0,0,C32/B32) | F32: =IF(B32=0,"",REPT("▓",MIN(20,INT(C32/B32*20)))&REPT("░",MAX(0,20-MIN(20,INT(C32/B32*20)))))
A34: 🏦 ÉPARGNE
A35: Livret A | B35: 0 | C35: 0 | D35: =B35-C35 | E35: =IF(B35=0,"—",C35/B35) | F35: =IF(B35=0,"",REPT("▓",MIN(20,INT(C35/B35*20)))&REPT("░",MAX(0,20-MIN(20,INT(C35/B35*20))))) | G35: =IF(C35=0,"⬜",IF(C35/B35<0.8,"🟢",IF(C35/B35<=1,"🟡","🔴")))
A36: PEL / CEL | B36: 0 | C36: 0 | D36: =B36-C36 | E36: =IF(B36=0,"—",C36/B36) | F36: =IF(B36=0,"",REPT("▓",MIN(20,INT(C36/B36*20)))&REPT("░",MAX(0,20-MIN(20,INT(C36/B36*20))))) | G36: =IF(C36=0,"⬜",IF(C36/B36<0.8,"🟢",IF(C36/B36<=1,"🟡","🔴")))
A37: Assurance-vie | B37: 0 | C37: 0 | D37: =B37-C37 | E37: =IF(B37=0,"—",C37/B37) | F37: =IF(B37=0,"",REPT("▓",MIN(20,INT(C37/B37*20)))&REPT("░",MAX(0,20-MIN(20,INT(C37/B37*20))))) | G37: =IF(C37=0,"⬜",IF(C37/B37<0.8,"🟢",IF(C37/B37<=1,"🟡","🔴")))
A38: Investissements | B38: 0 | C38: 0 | D38: =B38-C38 | E38: =IF(B38=0,"—",C38/B38) | F38: =IF(B38=0,"",REPT("▓",MIN(20,INT(C38/B38*20)))&REPT("░",MAX(0,20-MIN(20,INT(C38/B38*20))))) | G38: =IF(C38=0,"⬜",IF(C38/B38<0.8,"🟢",IF(C38/B38<=1,"🟡","🔴")))
A39: Total Épargne | B39: =SUM(B35:B38) | C39: =SUM(C35:C38) | D39: =SUM(D35:D38) | E39: =IF(B39=0,0,C39/B39) | F39: =IF(B39=0,"",REPT("▓",MIN(20,INT(C39/B39*20)))&REPT("░",MAX(0,20-MIN(20,INT(C39/B39*20)))))
A42: ✦ BILAN DU MOIS
A43: 💰 Total Revenus | F43: =C8
A44: 💸 Total Dépenses | F44: =C15+C26+C32
A45: 📊 Solde du mois | F45: =C8-(C15+C26+C32)
A46: 🎯 Taux d'épargne | F46: =IF(C8=0,0,(C8-(C15+C26+C32))/C8)
A47: 🏦 Épargne réelle | F47: =C39

Sheet Septembre
A1: ✦ SEPTEMBRE ✦
A2: Catégorie | B2: Budget prévu | C2: Réel dépensé | D2: Écart | E2: % utilisé | F2: Progression
A3: 💰 REVENUS
A4: Salaire net | B4: 0 | C4: 0 | D4: =B4-C4 | E4: =IF(B4=0,"—",C4/B4) | F4: =IF(B4=0,"",REPT("▓",MIN(20,INT(C4/B4*20)))&REPT("░",MAX(0,20-MIN(20,INT(C4/B4*20))))) | G4: =IF(C4=0,"⬜",IF(C4/B4<0.8,"🟢",IF(C4/B4<=1,"🟡","🔴")))
A5: Freelance / Side | B5: 0 | C5: 0 | D5: =B5-C5 | E5: =IF(B5=0,"—",C5/B5) | F5: =IF(B5=0,"",REPT("▓",MIN(20,INT(C5/B5*20)))&REPT("░",MAX(0,20-MIN(20,INT(C5/B5*20))))) | G5: =IF(C5=0,"⬜",IF(C5/B5<0.8,"🟢",IF(C5/B5<=1,"🟡","🔴")))
A6: Aides / APL | B6: 0 | C6: 0 | D6: =B6-C6 | E6: =IF(B6=0,"—",C6/B6) | F6: =IF(B6=0,"",REPT("▓",MIN(20,INT(C6/B6*20)))&REPT("░",MAX(0,20-MIN(20,INT(C6/B6*20))))) | G6: =IF(C6=0,"⬜",IF(C6/B6<0.8,"🟢",IF(C6/B6<=1,"🟡","🔴")))
A7: Autres revenus | B7: 0 | C7: 0 | D7: =B7-C7 | E7: =IF(B7=0,"—",C7/B7) | F7: =IF(B7=0,"",REPT("▓",MIN(20,INT(C7/B7*20)))&REPT("░",MAX(0,20-MIN(20,INT(C7/B7*20))))) | G7: =IF(C7=0,"⬜",IF(C7/B7<0.8,"🟢",IF(C7/B7<=1,"🟡","🔴")))
A8: Total Revenus | B8: =SUM(B4:B7) | C8: =SUM(C4:C7) | D8: =SUM(D4:D7) | E8: =IF(B8=0,0,C8/B8) | F8: =IF(B8=0,"",REPT("▓",MIN(20,INT(C8/B8*20)))&REPT("░",MAX(0,20-MIN(20,INT(C8/B8*20)))))
A10: 🏠 DÉPENSES FIXES
A11: Loyer / Crédit immo | B11: 0 | C11: 0 | D11: =B11-C11 | E11: =IF(B11=0,"—",C11/B11) | F11: =IF(B11=0,"",REPT("▓",MIN(20,INT(C11/B11*20)))&REPT("░",MAX(0,20-MIN(20,INT(C11/B11*20))))) | G11: =IF(C11=0,"⬜",IF(C11/B11<0.8,"🟢",IF(C11/B11<=1,"🟡","🔴")))
A12: Assurances | B12: 0 | C12: 0 | D12: =B12-C12 | E12: =IF(B12=0,"—",C12/B12) | F12: =IF(B12=0,"",REPT("▓",MIN(20,INT(C12/B12*20)))&REPT("░",MAX(0,20-MIN(20,INT(C12/B12*20))))) | G12: =IF(C12=0,"⬜",IF(C12/B12<0.8,"🟢",IF(C12/B12<=1,"🟡","🔴")))
A13: Abonnements | B13: 0 | C13: 0 | D13: =B13-C13 | E13: =IF(B13=0,"—",C13/B13) | F13: =IF(B13=0,"",REPT("▓",MIN(20,INT(C13/B13*20)))&REPT("░",MAX(0,20-MIN(20,INT(C13/B13*20))))) | G13: =IF(C13=0,"⬜",IF(C13/B13<0.8,"🟢",IF(C13/B13<=1,"🟡","🔴")))
A14: Téléphone / Internet | B14: 0 | C14: 0 | D14: =B14-C14 | E14: =IF(B14=0,"—",C14/B14) | F14: =IF(B14=0,"",REPT("▓",MIN(20,INT(C14/B14*20)))&REPT("░",MAX(0,20-MIN(20,INT(C14/B14*20))))) | G14: =IF(C14=0,"⬜",IF(C14/B14<0.8,"🟢",IF(C14/B14<=1,"🟡","🔴")))
A15: Total Fixes | B15: =SUM(B11:B14) | C15: =SUM(C11:C14) | D15: =SUM(D11:D14) | E15: =IF(B15=0,0,C15/B15) | F15: =IF(B15=0,"",REPT("▓",MIN(20,INT(C15/B15*20)))&REPT("░",MAX(0,20-MIN(20,INT(C15/B15*20)))))
A17: 🛒 DÉPENSES VARIABLES
A18: Alimentation | B18: 0 | C18: 0 | D18: =B18-C18 | E18: =IF(B18=0,"—",C18/B18) | F18: =IF(B18=0,"",REPT("▓",MIN(20,INT(C18/B18*20)))&REPT("░",MAX(0,20-MIN(20,INT(C18/B18*20))))) | G18: =IF(C18=0,"⬜",IF(C18/B18<0.8,"🟢",IF(C18/B18<=1,"🟡","🔴")))
A19: Transport | B19: 0 | C19: 0 | D19: =B19-C19 | E19: =IF(B19=0,"—",C19/B19) | F19: =IF(B19=0,"",REPT("▓",MIN(20,INT(C19/B19*20)))&REPT("░",MAX(0,20-MIN(20,INT(C19/B19*20))))) | G19: =IF(C19=0,"⬜",IF(C19/B19<0.8,"🟢",IF(C19/B19<=1,"🟡","🔴")))
A20: Santé | B20: 0 | C20: 0 | D20: =B20-C20 | E20: =IF(B20=0,"—",C20/B20) | F20: =IF(B20=0,"",REPT("▓",MIN(20,INT(C20/B20*20)))&REPT("░",MAX(0,20-MIN(20,INT(C20/B20*20))))) | G20: =IF(C20=0,"⬜",IF(C20/B20<0.8,"🟢",IF(C20/B20<=1,"🟡","🔴")))
A21: Loisirs | B21: 0 | C21: 0 | D21: =B21-C21 | E21: =IF(B21=0,"—",C21/B21) | F21: =IF(B21=0,"",REPT("▓",MIN(20,INT(C21/B21*20)))&REPT("░",MAX(0,20-MIN(20,INT(C21/B21*20))))) | G21: =IF(C21=0,"⬜",IF(C21/B21<0.8,"🟢",IF(C21/B21<=1,"🟡","🔴")))
A22: Shopping | B22: 0 | C22: 0 | D22: =B22-C22 | E22: =IF(B22=0,"—",C22/B22) | F22: =IF(B22=0,"",REPT("▓",MIN(20,INT(C22/B22*20)))&REPT("░",MAX(0,20-MIN(20,INT(C22/B22*20))))) | G22: =IF(C22=0,"⬜",IF(C22/B22<0.8,"🟢",IF(C22/B22<=1,"🟡","🔴")))
A23: Restaurant | B23: 0 | C23: 0 | D23: =B23-C23 | E23: =IF(B23=0,"—",C23/B23) | F23: =IF(B23=0,"",REPT("▓",MIN(20,INT(C23/B23*20)))&REPT("░",MAX(0,20-MIN(20,INT(C23/B23*20))))) | G23: =IF(C23=0,"⬜",IF(C23/B23<0.8,"🟢",IF(C23/B23<=1,"🟡","🔴")))
A24: Beauté | B24: 0 | C24: 0 | D24: =B24-C24 | E24: =IF(B24=0,"—",C24/B24) | F24: =IF(B24=0,"",REPT("▓",MIN(20,INT(C24/B24*20)))&REPT("░",MAX(0,20-MIN(20,INT(C24/B24*20))))) | G24: =IF(C24=0,"⬜",IF(C24/B24<0.8,"🟢",IF(C24/B24<=1,"🟡","🔴")))
A25: Autre | B25: 0 | C25: 0 | D25: =B25-C25 | E25: =IF(B25=0,"—",C25/B25) | F25: =IF(B25=0,"",REPT("▓",MIN(20,INT(C25/B25*20)))&REPT("░",MAX(0,20-MIN(20,INT(C25/B25*20))))) | G25: =IF(C25=0,"⬜",IF(C25/B25<0.8,"🟢",IF(C25/B25<=1,"🟡","🔴")))
A26: Total Variables | B26: =SUM(B18:B25) | C26: =SUM(C18:C25) | D26: =SUM(D18:D25) | E26: =IF(B26=0,0,C26/B26) | F26: =IF(B26=0,"",REPT("▓",MIN(20,INT(C26/B26*20)))&REPT("░",MAX(0,20-MIN(20,INT(C26/B26*20)))))
A28: 💳 CRÉDITS
A29: Crédit auto | B29: 0 | C29: 0 | D29: =B29-C29 | E29: =IF(B29=0,"—",C29/B29) | F29: =IF(B29=0,"",REPT("▓",MIN(20,INT(C29/B29*20)))&REPT("░",MAX(0,20-MIN(20,INT(C29/B29*20))))) | G29: =IF(C29=0,"⬜",IF(C29/B29<0.8,"🟢",IF(C29/B29<=1,"🟡","🔴")))
A30: Crédit conso | B30: 0 | C30: 0 | D30: =B30-C30 | E30: =IF(B30=0,"—",C30/B30) | F30: =IF(B30=0,"",REPT("▓",MIN(20,INT(C30/B30*20)))&REPT("░",MAX(0,20-MIN(20,INT(C30/B30*20))))) | G30: =IF(C30=0,"⬜",IF(C30/B30<0.8,"🟢",IF(C30/B30<=1,"🟡","🔴")))
A31: Autre crédit | B31: 0 | C31: 0 | D31: =B31-C31 | E31: =IF(B31=0,"—",C31/B31) | F31: =IF(B31=0,"",REPT("▓",MIN(20,INT(C31/B31*20)))&REPT("░",MAX(0,20-MIN(20,INT(C31/B31*20))))) | G31: =IF(C31=0,"⬜",IF(C31/B31<0.8,"🟢",IF(C31/B31<=1,"🟡","🔴")))
A32: Total Crédits | B32: =SUM(B29:B31) | C32: =SUM(C29:C31) | D32: =SUM(D29:D31) | E32: =IF(B32=0,0,C32/B32) | F32: =IF(B32=0,"",REPT("▓",MIN(20,INT(C32/B32*20)))&REPT("░",MAX(0,20-MIN(20,INT(C32/B32*20)))))
A34: 🏦 ÉPARGNE
A35: Livret A | B35: 0 | C35: 0 | D35: =B35-C35 | E35: =IF(B35=0,"—",C35/B35) | F35: =IF(B35=0,"",REPT("▓",MIN(20,INT(C35/B35*20)))&REPT("░",MAX(0,20-MIN(20,INT(C35/B35*20))))) | G35: =IF(C35=0,"⬜",IF(C35/B35<0.8,"🟢",IF(C35/B35<=1,"🟡","🔴")))
A36: PEL / CEL | B36: 0 | C36: 0 | D36: =B36-C36 | E36: =IF(B36=0,"—",C36/B36) | F36: =IF(B36=0,"",REPT("▓",MIN(20,INT(C36/B36*20)))&REPT("░",MAX(0,20-MIN(20,INT(C36/B36*20))))) | G36: =IF(C36=0,"⬜",IF(C36/B36<0.8,"🟢",IF(C36/B36<=1,"🟡","🔴")))
A37: Assurance-vie | B37: 0 | C37: 0 | D37: =B37-C37 | E37: =IF(B37=0,"—",C37/B37) | F37: =IF(B37=0,"",REPT("▓",MIN(20,INT(C37/B37*20)))&REPT("░",MAX(0,20-MIN(20,INT(C37/B37*20))))) | G37: =IF(C37=0,"⬜",IF(C37/B37<0.8,"🟢",IF(C37/B37<=1,"🟡","🔴")))
A38: Investissements | B38: 0 | C38: 0 | D38: =B38-C38 | E38: =IF(B38=0,"—",C38/B38) | F38: =IF(B38=0,"",REPT("▓",MIN(20,INT(C38/B38*20)))&REPT("░",MAX(0,20-MIN(20,INT(C38/B38*20))))) | G38: =IF(C38=0,"⬜",IF(C38/B38<0.8,"🟢",IF(C38/B38<=1,"🟡","🔴")))
A39: Total Épargne | B39: =SUM(B35:B38) | C39: =SUM(C35:C38) | D39: =SUM(D35:D38) | E39: =IF(B39=0,0,C39/B39) | F39: =IF(B39=0,"",REPT("▓",MIN(20,INT(C39/B39*20)))&REPT("░",MAX(0,20-MIN(20,INT(C39/B39*20)))))
A42: ✦ BILAN DU MOIS
A43: 💰 Total Revenus | F43: =C8
A44: 💸 Total Dépenses | F44: =C15+C26+C32
A45: 📊 Solde du mois | F45: =C8-(C15+C26+C32)
A46: 🎯 Taux d'épargne | F46: =IF(C8=0,0,(C8-(C15+C26+C32))/C8)
A47: 🏦 Épargne réelle | F47: =C39

Sheet Octobre
A1: ✦ OCTOBRE ✦
A2: Catégorie | B2: Budget prévu | C2: Réel dépensé | D2: Écart | E2: % utilisé | F2: Progression
A3: 💰 REVENUS
A4: Salaire net | B4: 0 | C4: 0 | D4: =B4-C4 | E4: =IF(B4=0,"—",C4/B4) | F4: =IF(B4=0,"",REPT("▓",MIN(20,INT(C4/B4*20)))&REPT("░",MAX(0,20-MIN(20,INT(C4/B4*20))))) | G4: =IF(C4=0,"⬜",IF(C4/B4<0.8,"🟢",IF(C4/B4<=1,"🟡","🔴")))
A5: Freelance / Side | B5: 0 | C5: 0 | D5: =B5-C5 | E5: =IF(B5=0,"—",C5/B5) | F5: =IF(B5=0,"",REPT("▓",MIN(20,INT(C5/B5*20)))&REPT("░",MAX(0,20-MIN(20,INT(C5/B5*20))))) | G5: =IF(C5=0,"⬜",IF(C5/B5<0.8,"🟢",IF(C5/B5<=1,"🟡","🔴")))
A6: Aides / APL | B6: 0 | C6: 0 | D6: =B6-C6 | E6: =IF(B6=0,"—",C6/B6) | F6: =IF(B6=0,"",REPT("▓",MIN(20,INT(C6/B6*20)))&REPT("░",MAX(0,20-MIN(20,INT(C6/B6*20))))) | G6: =IF(C6=0,"⬜",IF(C6/B6<0.8,"🟢",IF(C6/B6<=1,"🟡","🔴")))
A7: Autres revenus | B7: 0 | C7: 0 | D7: =B7-C7 | E7: =IF(B7=0,"—",C7/B7) | F7: =IF(B7=0,"",REPT("▓",MIN(20,INT(C7/B7*20)))&REPT("░",MAX(0,20-MIN(20,INT(C7/B7*20))))) | G7: =IF(C7=0,"⬜",IF(C7/B7<0.8,"🟢",IF(C7/B7<=1,"🟡","🔴")))
A8: Total Revenus | B8: =SUM(B4:B7) | C8: =SUM(C4:C7) | D8: =SUM(D4:D7) | E8: =IF(B8=0,0,C8/B8) | F8: =IF(B8=0,"",REPT("▓",MIN(20,INT(C8/B8*20)))&REPT("░",MAX(0,20-MIN(20,INT(C8/B8*20)))))
A10: 🏠 DÉPENSES FIXES
A11: Loyer / Crédit immo | B11: 0 | C11: 0 | D11: =B11-C11 | E11: =IF(B11=0,"—",C11/B11) | F11: =IF(B11=0,"",REPT("▓",MIN(20,INT(C11/B11*20)))&REPT("░",MAX(0,20-MIN(20,INT(C11/B11*20))))) | G11: =IF(C11=0,"⬜",IF(C11/B11<0.8,"🟢",IF(C11/B11<=1,"🟡","🔴")))
A12: Assurances | B12: 0 | C12: 0 | D12: =B12-C12 | E12: =IF(B12=0,"—",C12/B12) | F12: =IF(B12=0,"",REPT("▓",MIN(20,INT(C12/B12*20)))&REPT("░",MAX(0,20-MIN(20,INT(C12/B12*20))))) | G12: =IF(C12=0,"⬜",IF(C12/B12<0.8,"🟢",IF(C12/B12<=1,"🟡","🔴")))
A13: Abonnements | B13: 0 | C13: 0 | D13: =B13-C13 | E13: =IF(B13=0,"—",C13/B13) | F13: =IF(B13=0,"",REPT("▓",MIN(20,INT(C13/B13*20)))&REPT("░",MAX(0,20-MIN(20,INT(C13/B13*20))))) | G13: =IF(C13=0,"⬜",IF(C13/B13<0.8,"🟢",IF(C13/B13<=1,"🟡","🔴")))
A14: Téléphone / Internet | B14: 0 | C14: 0 | D14: =B14-C14 | E14: =IF(B14=0,"—",C14/B14) | F14: =IF(B14=0,"",REPT("▓",MIN(20,INT(C14/B14*20)))&REPT("░",MAX(0,20-MIN(20,INT(C14/B14*20))))) | G14: =IF(C14=0,"⬜",IF(C14/B14<0.8,"🟢",IF(C14/B14<=1,"🟡","🔴")))
A15: Total Fixes | B15: =SUM(B11:B14) | C15: =SUM(C11:C14) | D15: =SUM(D11:D14) | E15: =IF(B15=0,0,C15/B15) | F15: =IF(B15=0,"",REPT("▓",MIN(20,INT(C15/B15*20)))&REPT("░",MAX(0,20-MIN(20,INT(C15/B15*20)))))
A17: 🛒 DÉPENSES VARIABLES
A18: Alimentation | B18: 0 | C18: 0 | D18: =B18-C18 | E18: =IF(B18=0,"—",C18/B18) | F18: =IF(B18=0,"",REPT("▓",MIN(20,INT(C18/B18*20)))&REPT("░",MAX(0,20-MIN(20,INT(C18/B18*20))))) | G18: =IF(C18=0,"⬜",IF(C18/B18<0.8,"🟢",IF(C18/B18<=1,"🟡","🔴")))
A19: Transport | B19: 0 | C19: 0 | D19: =B19-C19 | E19: =IF(B19=0,"—",C19/B19) | F19: =IF(B19=0,"",REPT("▓",MIN(20,INT(C19/B19*20)))&REPT("░",MAX(0,20-MIN(20,INT(C19/B19*20))))) | G19: =IF(C19=0,"⬜",IF(C19/B19<0.8,"🟢",IF(C19/B19<=1,"🟡","🔴")))
A20: Santé | B20: 0 | C20: 0 | D20: =B20-C20 | E20: =IF(B20=0,"—",C20/B20) | F20: =IF(B20=0,"",REPT("▓",MIN(20,INT(C20/B20*20)))&REPT("░",MAX(0,20-MIN(20,INT(C20/B20*20))))) | G20: =IF(C20=0,"⬜",IF(C20/B20<0.8,"🟢",IF(C20/B20<=1,"🟡","🔴")))
A21: Loisirs | B21: 0 | C21: 0 | D21: =B21-C21 | E21: =IF(B21=0,"—",C21/B21) | F21: =IF(B21=0,"",REPT("▓",MIN(20,INT(C21/B21*20)))&REPT("░",MAX(0,20-MIN(20,INT(C21/B21*20))))) | G21: =IF(C21=0,"⬜",IF(C21/B21<0.8,"🟢",IF(C21/B21<=1,"🟡","🔴")))
A22: Shopping | B22: 0 | C22: 0 | D22: =B22-C22 | E22: =IF(B22=0,"—",C22/B22) | F22: =IF(B22=0,"",REPT("▓",MIN(20,INT(C22/B22*20)))&REPT("░",MAX(0,20-MIN(20,INT(C22/B22*20))))) | G22: =IF(C22=0,"⬜",IF(C22/B22<0.8,"🟢",IF(C22/B22<=1,"🟡","🔴")))
A23: Restaurant | B23: 0 | C23: 0 | D23: =B23-C23 | E23: =IF(B23=0,"—",C23/B23) | F23: =IF(B23=0,"",REPT("▓",MIN(20,INT(C23/B23*20)))&REPT("░",MAX(0,20-MIN(20,INT(C23/B23*20))))) | G23: =IF(C23=0,"⬜",IF(C23/B23<0.8,"🟢",IF(C23/B23<=1,"🟡","🔴")))
A24: Beauté | B24: 0 | C24: 0 | D24: =B24-C24 | E24: =IF(B24=0,"—",C24/B24) | F24: =IF(B24=0,"",REPT("▓",MIN(20,INT(C24/B24*20)))&REPT("░",MAX(0,20-MIN(20,INT(C24/B24*20))))) | G24: =IF(C24=0,"⬜",IF(C24/B24<0.8,"🟢",IF(C24/B24<=1,"🟡","🔴")))
A25: Autre | B25: 0 | C25: 0 | D25: =B25-C25 | E25: =IF(B25=0,"—",C25/B25) | F25: =IF(B25=0,"",REPT("▓",MIN(20,INT(C25/B25*20)))&REPT("░",MAX(0,20-MIN(20,INT(C25/B25*20))))) | G25: =IF(C25=0,"⬜",IF(C25/B25<0.8,"🟢",IF(C25/B25<=1,"🟡","🔴")))
A26: Total Variables | B26: =SUM(B18:B25) | C26: =SUM(C18:C25) | D26: =SUM(D18:D25) | E26: =IF(B26=0,0,C26/B26) | F26: =IF(B26=0,"",REPT("▓",MIN(20,INT(C26/B26*20)))&REPT("░",MAX(0,20-MIN(20,INT(C26/B26*20)))))
A28: 💳 CRÉDITS
A29: Crédit auto | B29: 0 | C29: 0 | D29: =B29-C29 | E29: =IF(B29=0,"—",C29/B29) | F29: =IF(B29=0,"",REPT("▓",MIN(20,INT(C29/B29*20)))&REPT("░",MAX(0,20-MIN(20,INT(C29/B29*20))))) | G29: =IF(C29=0,"⬜",IF(C29/B29<0.8,"🟢",IF(C29/B29<=1,"🟡","🔴")))
A30: Crédit conso | B30: 0 | C30: 0 | D30: =B30-C30 | E30: =IF(B30=0,"—",C30/B30) | F30: =IF(B30=0,"",REPT("▓",MIN(20,INT(C30/B30*20)))&REPT("░",MAX(0,20-MIN(20,INT(C30/B30*20))))) | G30: =IF(C30=0,"⬜",IF(C30/B30<0.8,"🟢",IF(C30/B30<=1,"🟡","🔴")))
A31: Autre crédit | B31: 0 | C31: 0 | D31: =B31-C31 | E31: =IF(B31=0,"—",C31/B31) | F31: =IF(B31=0,"",REPT("▓",MIN(20,INT(C31/B31*20)))&REPT("░",MAX(0,20-MIN(20,INT(C31/B31*20))))) | G31: =IF(C31=0,"⬜",IF(C31/B31<0.8,"🟢",IF(C31/B31<=1,"🟡","🔴")))
A32: Total Crédits | B32: =SUM(B29:B31) | C32: =SUM(C29:C31) | D32: =SUM(D29:D31) | E32: =IF(B32=0,0,C32/B32) | F32: =IF(B32=0,"",REPT("▓",MIN(20,INT(C32/B32*20)))&REPT("░",MAX(0,20-MIN(20,INT(C32/B32*20)))))
A34: 🏦 ÉPARGNE
A35: Livret A | B35: 0 | C35: 0 | D35: =B35-C35 | E35: =IF(B35=0,"—",C35/B35) | F35: =IF(B35=0,"",REPT("▓",MIN(20,INT(C35/B35*20)))&REPT("░",MAX(0,20-MIN(20,INT(C35/B35*20))))) | G35: =IF(C35=0,"⬜",IF(C35/B35<0.8,"🟢",IF(C35/B35<=1,"🟡","🔴")))
A36: PEL / CEL | B36: 0 | C36: 0 | D36: =B36-C36 | E36: =IF(B36=0,"—",C36/B36) | F36: =IF(B36=0,"",REPT("▓",MIN(20,INT(C36/B36*20)))&REPT("░",MAX(0,20-MIN(20,INT(C36/B36*20))))) | G36: =IF(C36=0,"⬜",IF(C36/B36<0.8,"🟢",IF(C36/B36<=1,"🟡","🔴")))
A37: Assurance-vie | B37: 0 | C37: 0 | D37: =B37-C37 | E37: =IF(B37=0,"—",C37/B37) | F37: =IF(B37=0,"",REPT("▓",MIN(20,INT(C37/B37*20)))&REPT("░",MAX(0,20-MIN(20,INT(C37/B37*20))))) | G37: =IF(C37=0,"⬜",IF(C37/B37<0.8,"🟢",IF(C37/B37<=1,"🟡","🔴")))
A38: Investissements | B38: 0 | C38: 0 | D38: =B38-C38 | E38: =IF(B38=0,"—",C38/B38) | F38: =IF(B38=0,"",REPT("▓",MIN(20,INT(C38/B38*20)))&REPT("░",MAX(0,20-MIN(20,INT(C38/B38*20))))) | G38: =IF(C38=0,"⬜",IF(C38/B38<0.8,"🟢",IF(C38/B38<=1,"🟡","🔴")))
A39: Total Épargne | B39: =SUM(B35:B38) | C39: =SUM(C35:C38) | D39: =SUM(D35:D38) | E39: =IF(B39=0,0,C39/B39) | F39: =IF(B39=0,"",REPT("▓",MIN(20,INT(C39/B39*20)))&REPT("░",MAX(0,20-MIN(20,INT(C39/B39*20)))))
A42: ✦ BILAN DU MOIS
A43: 💰 Total Revenus | F43: =C8
A44: 💸 Total Dépenses | F44: =C15+C26+C32
A45: 📊 Solde du mois | F45: =C8-(C15+C26+C32)
A46: 🎯 Taux d'épargne | F46: =IF(C8=0,0,(C8-(C15+C26+C32))/C8)
A47: 🏦 Épargne réelle | F47: =C39

Sheet Novembre
A1: ✦ NOVEMBRE ✦
A2: Catégorie | B2: Budget prévu | C2: Réel dépensé | D2: Écart | E2: % utilisé | F2: Progression
A3: 💰 REVENUS
A4: Salaire net | B4: 0 | C4: 0 | D4: =B4-C4 | E4: =IF(B4=0,"—",C4/B4) | F4: =IF(B4=0,"",REPT("▓",MIN(20,INT(C4/B4*20)))&REPT("░",MAX(0,20-MIN(20,INT(C4/B4*20))))) | G4: =IF(C4=0,"⬜",IF(C4/B4<0.8,"🟢",IF(C4/B4<=1,"🟡","🔴")))
A5: Freelance / Side | B5: 0 | C5: 0 | D5: =B5-C5 | E5: =IF(B5=0,"—",C5/B5) | F5: =IF(B5=0,"",REPT("▓",MIN(20,INT(C5/B5*20)))&REPT("░",MAX(0,20-MIN(20,INT(C5/B5*20))))) | G5: =IF(C5=0,"⬜",IF(C5/B5<0.8,"🟢",IF(C5/B5<=1,"🟡","🔴")))
A6: Aides / APL | B6: 0 | C6: 0 | D6: =B6-C6 | E6: =IF(B6=0,"—",C6/B6) | F6: =IF(B6=0,"",REPT("▓",MIN(20,INT(C6/B6*20)))&REPT("░",MAX(0,20-MIN(20,INT(C6/B6*20))))) | G6: =IF(C6=0,"⬜",IF(C6/B6<0.8,"🟢",IF(C6/B6<=1,"🟡","🔴")))
A7: Autres revenus | B7: 0 | C7: 0 | D7: =B7-C7 | E7: =IF(B7=0,"—",C7/B7) | F7: =IF(B7=0,"",REPT("▓",MIN(20,INT(C7/B7*20)))&REPT("░",MAX(0,20-MIN(20,INT(C7/B7*20))))) | G7: =IF(C7=0,"⬜",IF(C7/B7<0.8,"🟢",IF(C7/B7<=1,"🟡","🔴")))
A8: Total Revenus | B8: =SUM(B4:B7) | C8: =SUM(C4:C7) | D8: =SUM(D4:D7) | E8: =IF(B8=0,0,C8/B8) | F8: =IF(B8=0,"",REPT("▓",MIN(20,INT(C8/B8*20)))&REPT("░",MAX(0,20-MIN(20,INT(C8/B8*20)))))
A10: 🏠 DÉPENSES FIXES
A11: Loyer / Crédit immo | B11: 0 | C11: 0 | D11: =B11-C11 | E11: =IF(B11=0,"—",C11/B11) | F11: =IF(B11=0,"",REPT("▓",MIN(20,INT(C11/B11*20)))&REPT("░",MAX(0,20-MIN(20,INT(C11/B11*20))))) | G11: =IF(C11=0,"⬜",IF(C11/B11<0.8,"🟢",IF(C11/B11<=1,"🟡","🔴")))
A12: Assurances | B12: 0 | C12: 0 | D12: =B12-C12 | E12: =IF(B12=0,"—",C12/B12) | F12: =IF(B12=0,"",REPT("▓",MIN(20,INT(C12/B12*20)))&REPT("░",MAX(0,20-MIN(20,INT(C12/B12*20))))) | G12: =IF(C12=0,"⬜",IF(C12/B12<0.8,"🟢",IF(C12/B12<=1,"🟡","🔴")))
A13: Abonnements | B13: 0 | C13: 0 | D13: =B13-C13 | E13: =IF(B13=0,"—",C13/B13) | F13: =IF(B13=0,"",REPT("▓",MIN(20,INT(C13/B13*20)))&REPT("░",MAX(0,20-MIN(20,INT(C13/B13*20))))) | G13: =IF(C13=0,"⬜",IF(C13/B13<0.8,"🟢",IF(C13/B13<=1,"🟡","🔴")))
A14: Téléphone / Internet | B14: 0 | C14: 0 | D14: =B14-C14 | E14: =IF(B14=0,"—",C14/B14) | F14: =IF(B14=0,"",REPT("▓",MIN(20,INT(C14/B14*20)))&REPT("░",MAX(0,20-MIN(20,INT(C14/B14*20))))) | G14: =IF(C14=0,"⬜",IF(C14/B14<0.8,"🟢",IF(C14/B14<=1,"🟡","🔴")))
A15: Total Fixes | B15: =SUM(B11:B14) | C15: =SUM(C11:C14) | D15: =SUM(D11:D14) | E15: =IF(B15=0,0,C15/B15) | F15: =IF(B15=0,"",REPT("▓",MIN(20,INT(C15/B15*20)))&REPT("░",MAX(0,20-MIN(20,INT(C15/B15*20)))))
A17: 🛒 DÉPENSES VARIABLES
A18: Alimentation | B18: 0 | C18: 0 | D18: =B18-C18 | E18: =IF(B18=0,"—",C18/B18) | F18: =IF(B18=0,"",REPT("▓",MIN(20,INT(C18/B18*20)))&REPT("░",MAX(0,20-MIN(20,INT(C18/B18*20))))) | G18: =IF(C18=0,"⬜",IF(C18/B18<0.8,"🟢",IF(C18/B18<=1,"🟡","🔴")))
A19: Transport | B19: 0 | C19: 0 | D19: =B19-C19 | E19: =IF(B19=0,"—",C19/B19) | F19: =IF(B19=0,"",REPT("▓",MIN(20,INT(C19/B19*20)))&REPT("░",MAX(0,20-MIN(20,INT(C19/B19*20))))) | G19: =IF(C19=0,"⬜",IF(C19/B19<0.8,"🟢",IF(C19/B19<=1,"🟡","🔴")))
A20: Santé | B20: 0 | C20: 0 | D20: =B20-C20 | E20: =IF(B20=0,"—",C20/B20) | F20: =IF(B20=0,"",REPT("▓",MIN(20,INT(C20/B20*20)))&REPT("░",MAX(0,20-MIN(20,INT(C20/B20*20))))) | G20: =IF(C20=0,"⬜",IF(C20/B20<0.8,"🟢",IF(C20/B20<=1,"🟡","🔴")))
A21: Loisirs | B21: 0 | C21: 0 | D21: =B21-C21 | E21: =IF(B21=0,"—",C21/B21) | F21: =IF(B21=0,"",REPT("▓",MIN(20,INT(C21/B21*20)))&REPT("░",MAX(0,20-MIN(20,INT(C21/B21*20))))) | G21: =IF(C21=0,"⬜",IF(C21/B21<0.8,"🟢",IF(C21/B21<=1,"🟡","🔴")))
A22: Shopping | B22: 0 | C22: 0 | D22: =B22-C22 | E22: =IF(B22=0,"—",C22/B22) | F22: =IF(B22=0,"",REPT("▓",MIN(20,INT(C22/B22*20)))&REPT("░",MAX(0,20-MIN(20,INT(C22/B22*20))))) | G22: =IF(C22=0,"⬜",IF(C22/B22<0.8,"🟢",IF(C22/B22<=1,"🟡","🔴")))
A23: Restaurant | B23: 0 | C23: 0 | D23: =B23-C23 | E23: =IF(B23=0,"—",C23/B23) | F23: =IF(B23=0,"",REPT("▓",MIN(20,INT(C23/B23*20)))&REPT("░",MAX(0,20-MIN(20,INT(C23/B23*20))))) | G23: =IF(C23=0,"⬜",IF(C23/B23<0.8,"🟢",IF(C23/B23<=1,"🟡","🔴")))
A24: Beauté | B24: 0 | C24: 0 | D24: =B24-C24 | E24: =IF(B24=0,"—",C24/B24) | F24: =IF(B24=0,"",REPT("▓",MIN(20,INT(C24/B24*20)))&REPT("░",MAX(0,20-MIN(20,INT(C24/B24*20))))) | G24: =IF(C24=0,"⬜",IF(C24/B24<0.8,"🟢",IF(C24/B24<=1,"🟡","🔴")))
A25: Autre | B25: 0 | C25: 0 | D25: =B25-C25 | E25: =IF(B25=0,"—",C25/B25) | F25: =IF(B25=0,"",REPT("▓",MIN(20,INT(C25/B25*20)))&REPT("░",MAX(0,20-MIN(20,INT(C25/B25*20))))) | G25: =IF(C25=0,"⬜",IF(C25/B25<0.8,"🟢",IF(C25/B25<=1,"🟡","🔴")))
A26: Total Variables | B26: =SUM(B18:B25) | C26: =SUM(C18:C25) | D26: =SUM(D18:D25) | E26: =IF(B26=0,0,C26/B26) | F26: =IF(B26=0,"",REPT("▓",MIN(20,INT(C26/B26*20)))&REPT("░",MAX(0,20-MIN(20,INT(C26/B26*20)))))
A28: 💳 CRÉDITS
A29: Crédit auto | B29: 0 | C29: 0 | D29: =B29-C29 | E29: =IF(B29=0,"—",C29/B29) | F29: =IF(B29=0,"",REPT("▓",MIN(20,INT(C29/B29*20)))&REPT("░",MAX(0,20-MIN(20,INT(C29/B29*20))))) | G29: =IF(C29=0,"⬜",IF(C29/B29<0.8,"🟢",IF(C29/B29<=1,"🟡","🔴")))
A30: Crédit conso | B30: 0 | C30: 0 | D30: =B30-C30 | E30: =IF(B30=0,"—",C30/B30) | F30: =IF(B30=0,"",REPT("▓",MIN(20,INT(C30/B30*20)))&REPT("░",MAX(0,20-MIN(20,INT(C30/B30*20))))) | G30: =IF(C30=0,"⬜",IF(C30/B30<0.8,"🟢",IF(C30/B30<=1,"🟡","🔴")))
A31: Autre crédit | B31: 0 | C31: 0 | D31: =B31-C31 | E31: =IF(B31=0,"—",C31/B31) | F31: =IF(B31=0,"",REPT("▓",MIN(20,INT(C31/B31*20)))&REPT("░",MAX(0,20-MIN(20,INT(C31/B31*20))))) | G31: =IF(C31=0,"⬜",IF(C31/B31<0.8,"🟢",IF(C31/B31<=1,"🟡","🔴")))
A32: Total Crédits | B32: =SUM(B29:B31) | C32: =SUM(C29:C31) | D32: =SUM(D29:D31) | E32: =IF(B32=0,0,C32/B32) | F32: =IF(B32=0,"",REPT("▓",MIN(20,INT(C32/B32*20)))&REPT("░",MAX(0,20-MIN(20,INT(C32/B32*20)))))
A34: 🏦 ÉPARGNE
A35: Livret A | B35: 0 | C35: 0 | D35: =B35-C35 | E35: =IF(B35=0,"—",C35/B35) | F35: =IF(B35=0,"",REPT("▓",MIN(20,INT(C35/B35*20)))&REPT("░",MAX(0,20-MIN(20,INT(C35/B35*20))))) | G35: =IF(C35=0,"⬜",IF(C35/B35<0.8,"🟢",IF(C35/B35<=1,"🟡","🔴")))
A36: PEL / CEL | B36: 0 | C36: 0 | D36: =B36-C36 | E36: =IF(B36=0,"—",C36/B36) | F36: =IF(B36=0,"",REPT("▓",MIN(20,INT(C36/B36*20)))&REPT("░",MAX(0,20-MIN(20,INT(C36/B36*20))))) | G36: =IF(C36=0,"⬜",IF(C36/B36<0.8,"🟢",IF(C36/B36<=1,"🟡","🔴")))
A37: Assurance-vie | B37: 0 | C37: 0 | D37: =B37-C37 | E37: =IF(B37=0,"—",C37/B37) | F37: =IF(B37=0,"",REPT("▓",MIN(20,INT(C37/B37*20)))&REPT("░",MAX(0,20-MIN(20,INT(C37/B37*20))))) | G37: =IF(C37=0,"⬜",IF(C37/B37<0.8,"🟢",IF(C37/B37<=1,"🟡","🔴")))
A38: Investissements | B38: 0 | C38: 0 | D38: =B38-C38 | E38: =IF(B38=0,"—",C38/B38) | F38: =IF(B38=0,"",REPT("▓",MIN(20,INT(C38/B38*20)))&REPT("░",MAX(0,20-MIN(20,INT(C38/B38*20))))) | G38: =IF(C38=0,"⬜",IF(C38/B38<0.8,"🟢",IF(C38/B38<=1,"🟡","🔴")))
A39: Total Épargne | B39: =SUM(B35:B38) | C39: =SUM(C35:C38) | D39: =SUM(D35:D38) | E39: =IF(B39=0,0,C39/B39) | F39: =IF(B39=0,"",REPT("▓",MIN(20,INT(C39/B39*20)))&REPT("░",MAX(0,20-MIN(20,INT(C39/B39*20)))))
A42: ✦ BILAN DU MOIS
A43: 💰 Total Revenus | F43: =C8
A44: 💸 Total Dépenses | F44: =C15+C26+C32
A45: 📊 Solde du mois | F45: =C8-(C15+C26+C32)
A46: 🎯 Taux d'épargne | F46: =IF(C8=0,0,(C8-(C15+C26+C32))/C8)
A47: 🏦 Épargne réelle | F47: =C39

Sheet Decembre
A1: ✦ DÉCEMBRE ✦
A2: Catégorie | B2: Budget prévu | C2: Réel dépensé | D2: Écart | E2: % utilisé | F2: Progression
A3: 💰 REVENUS
A4: Salaire net | B4: 0 | C4: 0 | D4: =B4-C4 | E4: =IF(B4=0,"—",C4/B4) | F4: =IF(B4=0,"",REPT("▓",MIN(20,INT(C4/B4*20)))&REPT("░",MAX(0,20-MIN(20,INT(C4/B4*20))))) | G4: =IF(C4=0,"⬜",IF(C4/B4<0.8,"🟢",IF(C4/B4<=1,"🟡","🔴")))
A5: Freelance / Side | B5: 0 | C5: 0 | D5: =B5-C5 | E5: =IF(B5=0,"—",C5/B5) | F5: =IF(B5=0,"",REPT("▓",MIN(20,INT(C5/B5*20)))&REPT("░",MAX(0,20-MIN(20,INT(C5/B5*20))))) | G5: =IF(C5=0,"⬜",IF(C5/B5<0.8,"🟢",IF(C5/B5<=1,"🟡","🔴")))
A6: Aides / APL | B6: 0 | C6: 0 | D6: =B6-C6 | E6: =IF(B6=0,"—",C6/B6) | F6: =IF(B6=0,"",REPT("▓",MIN(20,INT(C6/B6*20)))&REPT("░",MAX(0,20-MIN(20,INT(C6/B6*20))))) | G6: =IF(C6=0,"⬜",IF(C6/B6<0.8,"🟢",IF(C6/B6<=1,"🟡","🔴")))
A7: Autres revenus | B7: 0 | C7: 0 | D7: =B7-C7 | E7: =IF(B7=0,"—",C7/B7) | F7: =IF(B7=0,"",REPT("▓",MIN(20,INT(C7/B7*20)))&REPT("░",MAX(0,20-MIN(20,INT(C7/B7*20))))) | G7: =IF(C7=0,"⬜",IF(C7/B7<0.8,"🟢",IF(C7/B7<=1,"🟡","🔴")))
A8: Total Revenus | B8: =SUM(B4:B7) | C8: =SUM(C4:C7) | D8: =SUM(D4:D7) | E8: =IF(B8=0,0,C8/B8) | F8: =IF(B8=0,"",REPT("▓",MIN(20,INT(C8/B8*20)))&REPT("░",MAX(0,20-MIN(20,INT(C8/B8*20)))))
A10: 🏠 DÉPENSES FIXES
A11: Loyer / Crédit immo | B11: 0 | C11: 0 | D11: =B11-C11 | E11: =IF(B11=0,"—",C11/B11) | F11: =IF(B11=0,"",REPT("▓",MIN(20,INT(C11/B11*20)))&REPT("░",MAX(0,20-MIN(20,INT(C11/B11*20))))) | G11: =IF(C11=0,"⬜",IF(C11/B11<0.8,"🟢",IF(C11/B11<=1,"🟡","🔴")))
A12: Assurances | B12: 0 | C12: 0 | D12: =B12-C12 | E12: =IF(B12=0,"—",C12/B12) | F12: =IF(B12=0,"",REPT("▓",MIN(20,INT(C12/B12*20)))&REPT("░",MAX(0,20-MIN(20,INT(C12/B12*20))))) | G12: =IF(C12=0,"⬜",IF(C12/B12<0.8,"🟢",IF(C12/B12<=1,"🟡","🔴")))
A13: Abonnements | B13: 0 | C13: 0 | D13: =B13-C13 | E13: =IF(B13=0,"—",C13/B13) | F13: =IF(B13=0,"",REPT("▓",MIN(20,INT(C13/B13*20)))&REPT("░",MAX(0,20-MIN(20,INT(C13/B13*20))))) | G13: =IF(C13=0,"⬜",IF(C13/B13<0.8,"🟢",IF(C13/B13<=1,"🟡","🔴")))
A14: Téléphone / Internet | B14: 0 | C14: 0 | D14: =B14-C14 | E14: =IF(B14=0,"—",C14/B14) | F14: =IF(B14=0,"",REPT("▓",MIN(20,INT(C14/B14*20)))&REPT("░",MAX(0,20-MIN(20,INT(C14/B14*20))))) | G14: =IF(C14=0,"⬜",IF(C14/B14<0.8,"🟢",IF(C14/B14<=1,"🟡","🔴")))
A15: Total Fixes | B15: =SUM(B11:B14) | C15: =SUM(C11:C14) | D15: =SUM(D11:D14) | E15: =IF(B15=0,0,C15/B15) | F15: =IF(B15=0,"",REPT("▓",MIN(20,INT(C15/B15*20)))&REPT("░",MAX(0,20-MIN(20,INT(C15/B15*20)))))
A17: 🛒 DÉPENSES VARIABLES
A18: Alimentation | B18: 0 | C18: 0 | D18: =B18-C18 | E18: =IF(B18=0,"—",C18/B18) | F18: =IF(B18=0,"",REPT("▓",MIN(20,INT(C18/B18*20)))&REPT("░",MAX(0,20-MIN(20,INT(C18/B18*20))))) | G18: =IF(C18=0,"⬜",IF(C18/B18<0.8,"🟢",IF(C18/B18<=1,"🟡","🔴")))
A19: Transport | B19: 0 | C19: 0 | D19: =B19-C19 | E19: =IF(B19=0,"—",C19/B19) | F19: =IF(B19=0,"",REPT("▓",MIN(20,INT(C19/B19*20)))&REPT("░",MAX(0,20-MIN(20,INT(C19/B19*20))))) | G19: =IF(C19=0,"⬜",IF(C19/B19<0.8,"🟢",IF(C19/B19<=1,"🟡","🔴")))
A20: Santé | B20: 0 | C20: 0 | D20: =B20-C20 | E20: =IF(B20=0,"—",C20/B20) | F20: =IF(B20=0,"",REPT("▓",MIN(20,INT(C20/B20*20)))&REPT("░",MAX(0,20-MIN(20,INT(C20/B20*20))))) | G20: =IF(C20=0,"⬜",IF(C20/B20<0.8,"🟢",IF(C20/B20<=1,"🟡","🔴")))
A21: Loisirs | B21: 0 | C21: 0 | D21: =B21-C21 | E21: =IF(B21=0,"—",C21/B21) | F21: =IF(B21=0,"",REPT("▓",MIN(20,INT(C21/B21*20)))&REPT("░",MAX(0,20-MIN(20,INT(C21/B21*20))))) | G21: =IF(C21=0,"⬜",IF(C21/B21<0.8,"🟢",IF(C21/B21<=1,"🟡","🔴")))
A22: Shopping | B22: 0 | C22: 0 | D22: =B22-C22 | E22: =IF(B22=0,"—",C22/B22) | F22: =IF(B22=0,"",REPT("▓",MIN(20,INT(C22/B22*20)))&REPT("░",MAX(0,20-MIN(20,INT(C22/B22*20))))) | G22: =IF(C22=0,"⬜",IF(C22/B22<0.8,"🟢",IF(C22/B22<=1,"🟡","🔴")))
A23: Restaurant | B23: 0 | C23: 0 | D23: =B23-C23 | E23: =IF(B23=0,"—",C23/B23) | F23: =IF(B23=0,"",REPT("▓",MIN(20,INT(C23/B23*20)))&REPT("░",MAX(0,20-MIN(20,INT(C23/B23*20))))) | G23: =IF(C23=0,"⬜",IF(C23/B23<0.8,"🟢",IF(C23/B23<=1,"🟡","🔴")))
A24: Beauté | B24: 0 | C24: 0 | D24: =B24-C24 | E24: =IF(B24=0,"—",C24/B24) | F24: =IF(B24=0,"",REPT("▓",MIN(20,INT(C24/B24*20)))&REPT("░",MAX(0,20-MIN(20,INT(C24/B24*20))))) | G24: =IF(C24=0,"⬜",IF(C24/B24<0.8,"🟢",IF(C24/B24<=1,"🟡","🔴")))
A25: Autre | B25: 0 | C25: 0 | D25: =B25-C25 | E25: =IF(B25=0,"—",C25/B25) | F25: =IF(B25=0,"",REPT("▓",MIN(20,INT(C25/B25*20)))&REPT("░",MAX(0,20-MIN(20,INT(C25/B25*20))))) | G25: =IF(C25=0,"⬜",IF(C25/B25<0.8,"🟢",IF(C25/B25<=1,"🟡","🔴")))
A26: Total Variables | B26: =SUM(B18:B25) | C26: =SUM(C18:C25) | D26: =SUM(D18:D25) | E26: =IF(B26=0,0,C26/B26) | F26: =IF(B26=0,"",REPT("▓",MIN(20,INT(C26/B26*20)))&REPT("░",MAX(0,20-MIN(20,INT(C26/B26*20)))))
A28: 💳 CRÉDITS
A29: Crédit auto | B29: 0 | C29: 0 | D29: =B29-C29 | E29: =IF(B29=0,"—",C29/B29) | F29: =IF(B29=0,"",REPT("▓",MIN(20,INT(C29/B29*20)))&REPT("░",MAX(0,20-MIN(20,INT(C29/B29*20))))) | G29: =IF(C29=0,"⬜",IF(C29/B29<0.8,"🟢",IF(C29/B29<=1,"🟡","🔴")))
A30: Crédit conso | B30: 0 | C30: 0 | D30: =B30-C30 | E30: =IF(B30=0,"—",C30/B30) | F30: =IF(B30=0,"",REPT("▓",MIN(20,INT(C30/B30*20)))&REPT("░",MAX(0,20-MIN(20,INT(C30/B30*20))))) | G30: =IF(C30=0,"⬜",IF(C30/B30<0.8,"🟢",IF(C30/B30<=1,"🟡","🔴")))
A31: Autre crédit | B31: 0 | C31: 0 | D31: =B31-C31 | E31: =IF(B31=0,"—",C31/B31) | F31: =IF(B31=0,"",REPT("▓",MIN(20,INT(C31/B31*20)))&REPT("░",MAX(0,20-MIN(20,INT(C31/B31*20))))) | G31: =IF(C31=0,"⬜",IF(C31/B31<0.8,"🟢",IF(C31/B31<=1,"🟡","🔴")))
A32: Total Crédits | B32: =SUM(B29:B31) | C32: =SUM(C29:C31) | D32: =SUM(D29:D31) | E32: =IF(B32=0,0,C32/B32) | F32: =IF(B32=0,"",REPT("▓",MIN(20,INT(C32/B32*20)))&REPT("░",MAX(0,20-MIN(20,INT(C32/B32*20)))))
A34: 🏦 ÉPARGNE
A35: Livret A | B35: 0 | C35: 0 | D35: =B35-C35 | E35: =IF(B35=0,"—",C35/B35) | F35: =IF(B35=0,"",REPT("▓",MIN(20,INT(C35/B35*20)))&REPT("░",MAX(0,20-MIN(20,INT(C35/B35*20))))) | G35: =IF(C35=0,"⬜",IF(C35/B35<0.8,"🟢",IF(C35/B35<=1,"🟡","🔴")))
A36: PEL / CEL | B36: 0 | C36: 0 | D36: =B36-C36 | E36: =IF(B36=0,"—",C36/B36) | F36: =IF(B36=0,"",REPT("▓",MIN(20,INT(C36/B36*20)))&REPT("░",MAX(0,20-MIN(20,INT(C36/B36*20))))) | G36: =IF(C36=0,"⬜",IF(C36/B36<0.8,"🟢",IF(C36/B36<=1,"🟡","🔴")))
A37: Assurance-vie | B37: 0 | C37: 0 | D37: =B37-C37 | E37: =IF(B37=0,"—",C37/B37) | F37: =IF(B37=0,"",REPT("▓",MIN(20,INT(C37/B37*20)))&REPT("░",MAX(0,20-MIN(20,INT(C37/B37*20))))) | G37: =IF(C37=0,"⬜",IF(C37/B37<0.8,"🟢",IF(C37/B37<=1,"🟡","🔴")))
A38: Investissements | B38: 0 | C38: 0 | D38: =B38-C38 | E38: =IF(B38=0,"—",C38/B38) | F38: =IF(B38=0,"",REPT("▓",MIN(20,INT(C38/B38*20)))&REPT("░",MAX(0,20-MIN(20,INT(C38/B38*20))))) | G38: =IF(C38=0,"⬜",IF(C38/B38<0.8,"🟢",IF(C38/B38<=1,"🟡","🔴")))
A39: Total Épargne | B39: =SUM(B35:B38) | C39: =SUM(C35:C38) | D39: =SUM(D35:D38) | E39: =IF(B39=0,0,C39/B39) | F39: =IF(B39=0,"",REPT("▓",MIN(20,INT(C39/B39*20)))&REPT("░",MAX(0,20-MIN(20,INT(C39/B39*20)))))
A42: ✦ BILAN DU MOIS
A43: 💰 Total Revenus | F43: =C8
A44: 💸 Total Dépenses | F44: =C15+C26+C32
A45: 📊 Solde du mois | F45: =C8-(C15+C26+C32)
A46: 🎯 Taux d'épargne | F46: =IF(C8=0,0,(C8-(C15+C26+C32))/C8)
A47: 🏦 Épargne réelle | F47: =C39

Sheet Dashboard
B2: ✦ VUE ANNUELLE — DASHBOARD ✦
B3: Synthèse automatique de vos 12 mois
B5: 💰 Revenus annuels | D5: 💸 Total dépenses | F5: 📊 Solde annuel
B6: =SUM(Data_Dash!B2:B13) | D6: =SUM(Data_Dash!C2:C13) | F6: =SUM(Data_Dash!D2:D13)
B8: 🏦 Épargne totale | D8: 📈 Taux épargne moy | F8: 🏆 Meilleur mois
B9: =SUM(Data_Dash!E2:E13) | D9: =IFERROR(SUM(Data_Dash!D2:D13)/SUM(Data_Dash!B2:B13),0) | F9: =MAX(Data_Dash!D2:D13)
B12: 📅 ÉVOLUTION MENSUELLE
B13: Mois | C13: Revenus | D13: Dépenses | E13: Solde | F13: Épargne | G13: Bilan
B14: Janvier | C14: =Data_Dash!B2 | D14: =Data_Dash!C2 | E14: =Data_Dash!D2 | F14: =Data_Dash!E2 | G14: =IF(E14>=0,"🟢 +"&TEXT(E14,"#,##0")&" €","🔴 "&TEXT(E14,"#,##0")&" €")
B15: Février | C15: =Data_Dash!B3 | D15: =Data_Dash!C3 | E15: =Data_Dash!D3 | F15: =Data_Dash!E3 | G15: =IF(E15>=0,"🟢 +"&TEXT(E15,"#,##0")&" €","🔴 "&TEXT(E15,"#,##0")&" €")
B16: Mars | C16: =Data_Dash!B4 | D16: =Data_Dash!C4 | E16: =Data_Dash!D4 | F16: =Data_Dash!E4 | G16: =IF(E16>=0,"🟢 +"&TEXT(E16,"#,##0")&" €","🔴 "&TEXT(E16,"#,##0")&" €")
B17: Avril | C17: =Data_Dash!B5 | D17: =Data_Dash!C5 | E17: =Data_Dash!D5 | F17: =Data_Dash!E5 | G17: =IF(E17>=0,"🟢 +"&TEXT(E17,"#,##0")&" €","🔴 "&TEXT(E17,"#,##0")&" €")
B18: Mai | C18: =Data_Dash!B6 | D18: =Data_Dash!C6 | E18: =Data_Dash!D6 | F18: =Data_Dash!E6 | G18: =IF(E18>=0,"🟢 +"&TEXT(E18,"#,##0")&" €","🔴 "&TEXT(E18,"#,##0")&" €")
B19: Juin | C19: =Data_Dash!B7 | D19: =Data_Dash!C7 | E19: =Data_Dash!D7 | F19: =Data_Dash!E7 | G19: =IF(E19>=0,"🟢 +"&TEXT(E19,"#,##0")&" €","🔴 "&TEXT(E19,"#,##0")&" €")
B20: Juillet | C20: =Data_Dash!B8 | D20: =Data_Dash!C8 | E20: =Data_Dash!D8 | F20: =Data_Dash!E8 | G20: =IF(E20>=0,"🟢 +"&TEXT(E20,"#,##0")&" €","🔴 "&TEXT(E20,"#,##0")&" €")
B21: Août | C21: =Data_Dash!B9 | D21: =Data_Dash!C9 | E21: =Data_Dash!D9 | F21: =Data_Dash!E9 | G21: =IF(E21>=0,"🟢 +"&TEXT(E21,"#,##0")&" €","🔴 "&TEXT(E21,"#,##0")&" €")
B22: Septembre | C22: =Data_Dash!B10 | D22: =Data_Dash!C10 | E22: =Data_Dash!D10 | F22: =Data_Dash!E10 | G22: =IF(E22>=0,"🟢 +"&TEXT(E22,"#,##0")&" €","🔴 "&TEXT(E22,"#,##0")&" €")
B23: Octobre | C23: =Data_Dash!B11 | D23: =Data_Dash!C11 | E23: =Data_Dash!D11 | F23: =Data_Dash!E11 | G23: =IF(E23>=0,"🟢 +"&TEXT(E23,"#,##0")&" €","🔴 "&TEXT(E23,"#,##0")&" €")
B24: Novembre | C24: =Data_Dash!B12 | D24: =Data_Dash!C12 | E24: =Data_Dash!D12 | F24: =Data_Dash!E12 | G24: =IF(E24>=0,"🟢 +"&TEXT(E24,"#,##0")&" €","🔴 "&TEXT(E24,"#,##0")&" €")
B25: Décembre | C25: =Data_Dash!B13 | D25: =Data_Dash!C13 | E25: =Data_Dash!D13 | F25: =Data_Dash!E13 | G25: =IF(E25>=0,"🟢 +"&TEXT(E25,"#,##0")&" €","🔴 "&TEXT(E25,"#,##0")&" €")
B26: TOTAL ANNUEL | C26: =SUM(Data_Dash!B2:Data_Dash!B13) | D26: =SUM(Data_Dash!C2:Data_Dash!C13) | E26: =SUM(Data_Dash!D2:Data_Dash!D13) | F26: =SUM(Data_Dash!E2:Data_Dash!E13)

Sheet Data_Dash
A1: Mois | B1: Revenus | C1: Dépenses | D1: Solde | E1: Épargne
A2: Janvier | B2: ='Janvier'!F43 | C2: ='Janvier'!F44 | D2: ='Janvier'!F45 | E2: ='Janvier'!F47
A3: Février | B3: ='Fevrier'!F43 | C3: ='Fevrier'!F44 | D3: ='Fevrier'!F45 | E3: ='Fevrier'!F47
A4: Mars | B4: ='Mars'!F43 | C4: ='Mars'!F44 | D4: ='Mars'!F45 | E4: ='Mars'!F47
A5: Avril | B5: ='Avril'!F43 | C5: ='Avril'!F44 | D5: ='Avril'!F45 | E5: ='Avril'!F47
A6: Mai | B6: ='Mai'!F43 | C6: ='Mai'!F44 | D6: ='Mai'!F45 | E6: ='Mai'!F47
A7: Juin | B7: ='Juin'!F43 | C7: ='Juin'!F44 | D7: ='Juin'!F45 | E7: ='Juin'!F47
A8: Juillet | B8: ='Juillet'!F43 | C8: ='Juillet'!F44 | D8: ='Juillet'!F45 | E8: ='Juillet'!F47
A9: Août | B9: ='Aout'!F43 | C9: ='Aout'!F44 | D9: ='Aout'!F45 | E9: ='Aout'!F47
A10: Septembre | B10: ='Septembre'!F43 | C10: ='Septembre'!F44 | D10: ='Septembre'!F45 | E10: ='Septembre'!F47
A11: Octobre | B11: ='Octobre'!F43 | C11: ='Octobre'!F44 | D11: ='Octobre'!F45 | E11: ='Octobre'!F47
A12: Novembre | B12: ='Novembre'!F43 | C12: ='Novembre'!F44 | D12: ='Novembre'!F45 | E12: ='Novembre'!F47
A13: Décembre | B13: ='Decembre'!F43 | C13: ='Decembre'!F44 | D13: ='Decembre'!F45 | E13: ='Decembre'!F47
G16: Section | H16: Total annuel
G17: Dépenses fixes | H17: =SUM(Data_Dash!C2:C13)*4/19
G18: Dépenses variables | H18: =SUM(Data_Dash!C2:C13)*8/19
G19: Crédits | H19: =SUM(Data_Dash!C2:C13)*3/19
G20: Épargne | H20: =SUM(Data_Dash!C2:C13)*4/19
